{
  "version": "6.1.3",
  "objects": [
    {
      "id": "Number-of-Events",
      "type": "visualization",
      "updated_at": "2018-02-04T17:12:44.563Z",
      "version": 2,
      "attributes": {
        "title": "Number of Events",
        "visState": "{\"title\":\"Number of Events\",\"type\":\"metric\",\"params\":{\"fontSize\":60,\"addTooltip\":true,\"addLegend\":false,\"type\":\"metric\",\"metric\":{\"percentageMode\":false,\"useRanges\":false,\"colorSchema\":\"Green to Red\",\"metricColorMode\":\"None\",\"colorsRange\":[{\"from\":0,\"to\":10000}],\"labels\":{\"show\":false},\"invertColors\":false,\"style\":{\"bgFill\":\"#000\",\"bgColor\":false,\"labelColor\":false,\"subText\":\"\",\"fontSize\":20}}},\"aggs\":[{\"id\":\"1\",\"enabled\":true,\"type\":\"count\",\"schema\":\"metric\",\"params\":{}}]}",
        "uiStateJSON": "{}",
        "description": "",
        "version": 1,
        "kibanaSavedObjectMeta": {
          "searchSourceJSON": "{\"index\":\"winlogbeat-*\",\"query\":{\"query\":{\"query_string\":{\"query\":\"*\",\"analyze_wildcard\":true,\"default_field\":\"*\"}},\"language\":\"lucene\"},\"filter\":[]}"
        }
      }
    },
    {
      "id": "Number-of-Events-Over-Time-By-Event-Log",
      "type": "visualization",
      "updated_at": "2018-02-04T14:12:01.009Z",
      "version": 1,
      "attributes": {
        "description": "",
        "kibanaSavedObjectMeta": {
          "searchSourceJSON": "{\n  \"index\": \"winlogbeat-*\",\n  \"query\": {\n    \"query_string\": {\n      \"query\": \"*\",\n      \"analyze_wildcard\": true\n    }\n  },\n  \"filter\": []\n}"
        },
        "title": "Number of Events Over Time By Event Log",
        "uiStateJSON": "{}",
        "version": 1,
        "visState": "{\n  \"type\": \"histogram\",\n  \"params\": {\n    \"shareYAxis\": true,\n    \"addTooltip\": true,\n    \"addLegend\": true,\n    \"scale\": \"linear\",\n    \"mode\": \"stacked\",\n    \"times\": [],\n    \"addTimeMarker\": false,\n    \"defaultYExtents\": false,\n    \"setYExtents\": false,\n    \"yAxis\": {}\n  },\n  \"aggs\": [\n    {\n      \"id\": \"1\",\n      \"type\": \"count\",\n      \"schema\": \"metric\",\n      \"params\": {}\n    },\n    {\n      \"id\": \"2\",\n      \"type\": \"date_histogram\",\n      \"schema\": \"segment\",\n      \"params\": {\n        \"field\": \"@timestamp\",\n        \"interval\": \"auto\",\n        \"customInterval\": \"2h\",\n        \"min_doc_count\": 1,\n        \"extended_bounds\": {}\n      }\n    },\n    {\n      \"id\": \"3\",\n      \"type\": \"terms\",\n      \"schema\": \"group\",\n      \"params\": {\n        \"field\": \"log_name\",\n        \"size\": 6,\n        \"order\": \"desc\",\n        \"orderBy\": \"1\"\n      }\n    }\n  ],\n  \"listeners\": {}\n}"
      }
    },
    {
      "id": "NMAP-hosts-by-subnet-table",
      "type": "visualization",
      "updated_at": "2018-02-04T14:12:01.310Z",
      "version": 1,
      "attributes": {
        "savedSearchId": "NMAP-common-search",
        "description": "",
        "uiStateJSON": "{}",
        "title": "NMAP-хосты-по-сетям",
        "version": 1,
        "kibanaSavedObjectMeta": {
          "searchSourceJSON": "{\"filter\":[]}"
        },
        "visState": "{\"title\":\"NMAP-хосты-по-сетям\",\"type\":\"table\",\"params\":{\"perPage\":5,\"showPartialRows\":false,\"showMeticsAtAllLevels\":false},\"aggs\":[{\"id\":\"1\",\"type\":\"cardinality\",\"schema\":\"metric\",\"params\":{\"field\":\"ipv4\",\"customLabel\":\"Кол-во IP адресов\"}},{\"id\":\"2\",\"type\":\"terms\",\"schema\":\"bucket\",\"params\":{\"field\":\"headers.http_x_nmap_target\",\"size\":100,\"order\":\"asc\",\"orderBy\":\"_term\",\"customLabel\":\"Сети\"}}],\"listeners\":{}}"
      }
    },
    {
      "id": "f24a7060-0a7b-11e8-a2ce-b9829bf5932d",
      "type": "visualization",
      "updated_at": "2018-02-05T13:56:09.547Z",
      "version": 2,
      "attributes": {
        "title": "reffer",
        "visState": "{\"title\":\"reffer\",\"type\":\"markdown\",\"params\":{\"fontSize\":12,\"markdown\":\"# LittleBeat 6.1\\n### Список ссылок\\n_используйте правую кнопку мыши, чтобы открывать ссылку в новой вкладке браузера_   \\n_Для возврата к этой панели нажмите на логотип в левом верхнем углу_\\n\\n| Ссылка | &nbsp; &nbsp;   | Описание |\\n| ------------ | --- | -------------- | \\n| [Обнаруженные хосты](/app/kibana#/dashboard/NMAP-dash) |&nbsp; | эта панель содержит данные о хостах обнаруженных в сети и открытых портах.|\\n| [Общая панель Windows](/app/kibana#/dashboard/Winlogbeat-Dashboard) |&nbsp; | эта панель содержит данные о всех событиях, зарегистрированных на хостах Windows|\\n| [Панель Windows Logon](/app/kibana#/dashboard/2a808400-0a5a-11e8-a2ce-b9829bf5932d) |&nbsp;  | эта панель содержит информацию о событиях входа пользователей Windows (удачных и неудачных)|\\n| [Панель процессов и служб](/app/kibana#/dashboard/ceb2fb80-0a5e-11e8-a2ce-b9829bf5932d) | &nbsp;| эта панель содержит данные о запуске процессов и установке системных служб на хостах Windows|\\n| [Windows High Level](/app/kibana#/dashboard/d5ebbbc0-0a69-11e8-a2ce-b9829bf5932d) | &nbsp;| эта панель содержит данные журналов событий Windows на которые следует обращать особое внимание, согласно рекомендациям компании Microsoft.|  \\n\\n### Краткая инструкция:\\n\\nЕсли вы не видите событий Windows, значит, вы не установили агенты **LittleBeat** на компьютеры. Как это сделать?\\n\\n**Способ первый. Групповые политики**\\n\\nЕсли у вас есть контроллер домена AD, вы можете развернуть агента на все компьютеры в домене с помощью групповых политик.   \\nДля этого вам нужно загрузить два файла [littlebeat_agent_32.msi](https://github.com/ESGuardian/LittleBeat/raw/v-6.1.001/agents/bin/littlebeat_agent_32.msi) и  [littlebeat_agent_64.msi](https://github.com/ESGuardian/LittleBeat/raw/v-6.1.001/agents/bin/littlebeat_agent_64.msi). их можно использовать в групповых политиках \\\"на компьютер\\\" для систем соответствующей разрядности.\\n\\n**Способ второй. Установка на отдельный компьютер**\\n\\nВам следует использовать файл [littlebeat_agent.exe](https://github.com/ESGuardian/LittleBeat/raw/v-6.1.001/agents/bin/littlebeat_agent.exe). Это SFX архив с упомянутыми файлами msi и небольшим батником, который определяет версию системы и вызывает установщик Windows с нужной версией пакета. Запускать от имени администратора.\\n\\n**Способ третий. Централизованная установка с использованием утилиты PsExec**\\n\\nВы можете загрузить утилиту PsExec [отсюда](https://docs.microsoft.com/en-us/sysinternals/downloads/psexec).\\n\\n1. На рабочей станции windows, с которой вы будете производить\\n   установку на другие компьютеры создайте каталог `c:\\\\work`\\n   (можно с любым другим именем).\\n\\n2. Cкопируйте в этот каталог файлы:  \\n```\\nlittlebeat_agent.exe\\nPsExec.exe\\n```\\n3. Подготовьте в этом каталоге файл `list.txt` со списками имен (или IP адресов) компьютеров,\\n   на которые вы хотите установить агентов. Формат\\n   списка: одно имя (или IP адрес) в строке.\\n\\n4. Запустите командную строку (cmd.exe) и перейдите в каталог c:\\\\work\\n```   \\ncd \\\\work\\n```\\n5. Выполните команду:\\n```   \\npsexec @list.txt -u domain\\\\adminuser -p password -c -h -f littlebeat_agent.exe\\n```\\n   где `domain\\\\adminuser` - имя пользователя с административными правами на хостах\\n   (например, администратора домена),  \\n   `password` - пароль этого пользователя\\n\\n**Если вы ничего не видите на дашборде NMAP**, значит вы не настроили обзор сетей на консоли Littlebeat или ни разу не запускали его. Обзор сетей запускается автоматически каждые два часа, но вы можете запустить его прямо сейчас с консоли сервера Littlebeat. Имеется ввиду физическая консоль или консоль SSH.   \\n\\n**Совет:** если вы используете PuTTY, то в окне конфигурации в разделе `Connection`, в подразделе `Data`, в окошке `terminal-type string` напишите `linux` вместо `xterm`, иначе псевдографика в меню будет выглядеть смешно.  \\n\\nЕсли на дашборде NMAP вы не увидели имена хостов, только IP адреса, значит на вашем сервере  DNS нет записей PTR. Это не страшно, просто неудобно, лучше иметь.   \\n\\nБолее подробную документацию следует смотреть на [LittleBeat Wiki](https://github.com/ESGuardian/LittleBeat/wiki).\"},\"aggs\":[]}",
        "uiStateJSON": "{}",
        "description": "",
        "version": 1,
        "kibanaSavedObjectMeta": {
          "searchSourceJSON": "{}"
        }
      }
    },
    {
      "id": "winlogbeat-*",
      "type": "index-pattern",
      "updated_at": "2018-02-05T11:14:45.950Z",
      "version": 20,
      "attributes": {
        "fieldFormatMap": "{\"@timestamp\":{\"id\":\"date\"}}",
        "fields": "[{\"name\":\"@timestamp\",\"type\":\"date\",\"count\":0,\"scripted\":false,\"searchable\":true,\"aggregatable\":true,\"readFromDocValues\":true},{\"name\":\"@version\",\"type\":\"string\",\"count\":0,\"scripted\":false,\"searchable\":true,\"aggregatable\":true,\"readFromDocValues\":true},{\"name\":\"_id\",\"type\":\"string\",\"count\":0,\"scripted\":false,\"searchable\":true,\"aggregatable\":true,\"readFromDocValues\":false},{\"name\":\"_index\",\"type\":\"string\",\"count\":0,\"scripted\":false,\"searchable\":true,\"aggregatable\":true,\"readFromDocValues\":false},{\"name\":\"_score\",\"type\":\"number\",\"count\":0,\"scripted\":false,\"searchable\":false,\"aggregatable\":false,\"readFromDocValues\":false},{\"name\":\"_source\",\"type\":\"_source\",\"count\":0,\"scripted\":false,\"searchable\":false,\"aggregatable\":false,\"readFromDocValues\":false},{\"name\":\"_type\",\"type\":\"string\",\"count\":0,\"scripted\":false,\"searchable\":true,\"aggregatable\":true,\"readFromDocValues\":false},{\"name\":\"activity_id\",\"type\":\"string\",\"count\":0,\"scripted\":false,\"searchable\":true,\"aggregatable\":true,\"readFromDocValues\":true},{\"name\":\"beat.hostname\",\"type\":\"string\",\"count\":1,\"scripted\":false,\"searchable\":true,\"aggregatable\":true,\"readFromDocValues\":true},{\"name\":\"beat.name\",\"type\":\"string\",\"count\":0,\"scripted\":false,\"searchable\":true,\"aggregatable\":true,\"readFromDocValues\":true},{\"name\":\"beat.timezone\",\"type\":\"string\",\"count\":0,\"scripted\":false,\"searchable\":true,\"aggregatable\":true,\"readFromDocValues\":true},{\"name\":\"beat.version\",\"type\":\"string\",\"count\":0,\"scripted\":false,\"searchable\":true,\"aggregatable\":true,\"readFromDocValues\":true},{\"name\":\"computer_name\",\"type\":\"string\",\"count\":2,\"scripted\":false,\"searchable\":true,\"aggregatable\":true,\"readFromDocValues\":true},{\"name\":\"docker.container.id\",\"type\":\"string\",\"count\":0,\"scripted\":false,\"searchable\":true,\"aggregatable\":true,\"readFromDocValues\":true},{\"name\":\"docker.container.image\",\"type\":\"string\",\"count\":0,\"scripted\":false,\"searchable\":true,\"aggregatable\":true,\"readFromDocValues\":true},{\"name\":\"docker.container.name\",\"type\":\"string\",\"count\":0,\"scripted\":false,\"searchable\":true,\"aggregatable\":true,\"readFromDocValues\":true},{\"name\":\"error.code\",\"type\":\"number\",\"count\":0,\"scripted\":false,\"searchable\":true,\"aggregatable\":true,\"readFromDocValues\":true},{\"name\":\"error.message\",\"type\":\"string\",\"count\":0,\"scripted\":false,\"searchable\":true,\"aggregatable\":false,\"readFromDocValues\":false},{\"name\":\"error.type\",\"type\":\"string\",\"count\":0,\"scripted\":false,\"searchable\":true,\"aggregatable\":true,\"readFromDocValues\":true},{\"name\":\"event_data.AbandonedBatteryCount\",\"type\":\"string\",\"count\":0,\"scripted\":false,\"searchable\":true,\"aggregatable\":true,\"readFromDocValues\":true},{\"name\":\"event_data.AcOnline\",\"type\":\"string\",\"count\":0,\"scripted\":false,\"searchable\":true,\"aggregatable\":true,\"readFromDocValues\":true},{\"name\":\"event_data.AccountExpires\",\"type\":\"string\",\"count\":0,\"scripted\":false,\"searchable\":true,\"aggregatable\":true,\"readFromDocValues\":true},{\"name\":\"event_data.AccountName\",\"type\":\"string\",\"count\":0,\"scripted\":false,\"searchable\":true,\"aggregatable\":true,\"readFromDocValues\":true},{\"name\":\"event_data.AdapterName\",\"type\":\"string\",\"count\":0,\"scripted\":false,\"searchable\":true,\"aggregatable\":true,\"readFromDocValues\":true},{\"name\":\"event_data.AdapterSuffixName\",\"type\":\"string\",\"count\":0,\"scripted\":false,\"searchable\":true,\"aggregatable\":true,\"readFromDocValues\":true},{\"name\":\"event_data.Address\",\"type\":\"string\",\"count\":0,\"scripted\":false,\"searchable\":true,\"aggregatable\":true,\"readFromDocValues\":true},{\"name\":\"event_data.AddressLength\",\"type\":\"string\",\"count\":0,\"scripted\":false,\"searchable\":true,\"aggregatable\":true,\"readFromDocValues\":true},{\"name\":\"event_data.AdvancedOptions\",\"type\":\"string\",\"count\":0,\"scripted\":false,\"searchable\":true,\"aggregatable\":true,\"readFromDocValues\":true},{\"name\":\"event_data.AlgorithmName\",\"type\":\"string\",\"count\":0,\"scripted\":false,\"searchable\":true,\"aggregatable\":true,\"readFromDocValues\":true},{\"name\":\"event_data.AllowedToDelegateTo\",\"type\":\"string\",\"count\":0,\"scripted\":false,\"searchable\":true,\"aggregatable\":true,\"readFromDocValues\":true},{\"name\":\"event_data.Attributes\",\"type\":\"string\",\"count\":0,\"scripted\":false,\"searchable\":true,\"aggregatable\":true,\"readFromDocValues\":true},{\"name\":\"event_data.AuditPolicyChanges\",\"type\":\"string\",\"count\":0,\"scripted\":false,\"searchable\":true,\"aggregatable\":true,\"readFromDocValues\":true},{\"name\":\"event_data.AuditSourceName\",\"type\":\"string\",\"count\":0,\"scripted\":false,\"searchable\":true,\"aggregatable\":true,\"readFromDocValues\":true},{\"name\":\"event_data.AuthenticationPackageName\",\"type\":\"string\",\"count\":0,\"scripted\":false,\"searchable\":true,\"aggregatable\":true,\"readFromDocValues\":true},{\"name\":\"event_data.AverageResume\",\"type\":\"string\",\"count\":0,\"scripted\":false,\"searchable\":true,\"aggregatable\":true,\"readFromDocValues\":true},{\"name\":\"event_data.Binary\",\"type\":\"string\",\"count\":0,\"scripted\":false,\"searchable\":true,\"aggregatable\":true,\"readFromDocValues\":true},{\"name\":\"event_data.BiosInitDuration\",\"type\":\"string\",\"count\":0,\"scripted\":false,\"searchable\":true,\"aggregatable\":true,\"readFromDocValues\":true},{\"name\":\"event_data.BitlockerUserInputTime\",\"type\":\"string\",\"count\":0,\"scripted\":false,\"searchable\":true,\"aggregatable\":true,\"readFromDocValues\":true},{\"name\":\"event_data.BootAppStatus\",\"type\":\"string\",\"count\":0,\"scripted\":false,\"searchable\":true,\"aggregatable\":true,\"readFromDocValues\":true},{\"name\":\"event_data.BootMenuPolicy\",\"type\":\"string\",\"count\":0,\"scripted\":false,\"searchable\":true,\"aggregatable\":true,\"readFromDocValues\":true},{\"name\":\"event_data.BootMode\",\"type\":\"string\",\"count\":0,\"scripted\":false,\"searchable\":true,\"aggregatable\":true,\"readFromDocValues\":true},{\"name\":\"event_data.BootStatusPolicy\",\"type\":\"string\",\"count\":0,\"scripted\":false,\"searchable\":true,\"aggregatable\":true,\"readFromDocValues\":true},{\"name\":\"event_data.BootType\",\"type\":\"string\",\"count\":0,\"scripted\":false,\"searchable\":true,\"aggregatable\":true,\"readFromDocValues\":true},{\"name\":\"event_data.BugcheckCode\",\"type\":\"string\",\"count\":0,\"scripted\":false,\"searchable\":true,\"aggregatable\":true,\"readFromDocValues\":true},{\"name\":\"event_data.BugcheckInfoFromEFI\",\"type\":\"string\",\"count\":0,\"scripted\":false,\"searchable\":true,\"aggregatable\":true,\"readFromDocValues\":true},{\"name\":\"event_data.BugcheckParameter1\",\"type\":\"string\",\"count\":0,\"scripted\":false,\"searchable\":true,\"aggregatable\":true,\"readFromDocValues\":true},{\"name\":\"event_data.BugcheckParameter2\",\"type\":\"string\",\"count\":0,\"scripted\":false,\"searchable\":true,\"aggregatable\":true,\"readFromDocValues\":true},{\"name\":\"event_data.BugcheckParameter3\",\"type\":\"string\",\"count\":0,\"scripted\":false,\"searchable\":true,\"aggregatable\":true,\"readFromDocValues\":true},{\"name\":\"event_data.BugcheckParameter4\",\"type\":\"string\",\"count\":0,\"scripted\":false,\"searchable\":true,\"aggregatable\":true,\"readFromDocValues\":true},{\"name\":\"event_data.BuildVersion\",\"type\":\"string\",\"count\":0,\"scripted\":false,\"searchable\":true,\"aggregatable\":true,\"readFromDocValues\":true},{\"name\":\"event_data.CallerProcessId\",\"type\":\"string\",\"count\":0,\"scripted\":false,\"searchable\":true,\"aggregatable\":true,\"readFromDocValues\":true},{\"name\":\"event_data.CallerProcessName\",\"type\":\"string\",\"count\":0,\"scripted\":false,\"searchable\":true,\"aggregatable\":true,\"readFromDocValues\":true},{\"name\":\"event_data.CapDurationInSeconds\",\"type\":\"string\",\"count\":0,\"scripted\":false,\"searchable\":true,\"aggregatable\":true,\"readFromDocValues\":true},{\"name\":\"event_data.CategoryId\",\"type\":\"string\",\"count\":0,\"scripted\":false,\"searchable\":true,\"aggregatable\":true,\"readFromDocValues\":true},{\"name\":\"event_data.Checkpoint\",\"type\":\"string\",\"count\":0,\"scripted\":false,\"searchable\":true,\"aggregatable\":true,\"readFromDocValues\":true},{\"name\":\"event_data.ComputerName\",\"type\":\"string\",\"count\":0,\"scripted\":false,\"searchable\":true,\"aggregatable\":true,\"readFromDocValues\":true},{\"name\":\"event_data.Config\",\"type\":\"string\",\"count\":0,\"scripted\":false,\"searchable\":true,\"aggregatable\":true,\"readFromDocValues\":true},{\"name\":\"event_data.ConfigAccessPolicy\",\"type\":\"string\",\"count\":0,\"scripted\":false,\"searchable\":true,\"aggregatable\":true,\"readFromDocValues\":true},{\"name\":\"event_data.ConnectedStandbyInProgress\",\"type\":\"string\",\"count\":0,\"scripted\":false,\"searchable\":true,\"aggregatable\":true,\"readFromDocValues\":true},{\"name\":\"event_data.CorruptionActionState\",\"type\":\"string\",\"count\":0,\"scripted\":false,\"searchable\":true,\"aggregatable\":true,\"readFromDocValues\":true},{\"name\":\"event_data.CsEntryScenarioInstanceId\",\"type\":\"string\",\"count\":0,\"scripted\":false,\"searchable\":true,\"aggregatable\":true,\"readFromDocValues\":true},{\"name\":\"event_data.DCName\",\"type\":\"string\",\"count\":0,\"scripted\":false,\"searchable\":true,\"aggregatable\":true,\"readFromDocValues\":true},{\"name\":\"event_data.Default SD String:\",\"type\":\"string\",\"count\":0,\"scripted\":false,\"searchable\":true,\"aggregatable\":true,\"readFromDocValues\":true},{\"name\":\"event_data.Detail\",\"type\":\"string\",\"count\":0,\"scripted\":false,\"searchable\":true,\"aggregatable\":true,\"readFromDocValues\":true},{\"name\":\"event_data.DeviceInstance\",\"type\":\"string\",\"count\":0,\"scripted\":false,\"searchable\":true,\"aggregatable\":true,\"readFromDocValues\":true},{\"name\":\"event_data.DeviceInstanceLength\",\"type\":\"string\",\"count\":0,\"scripted\":false,\"searchable\":true,\"aggregatable\":true,\"readFromDocValues\":true},{\"name\":\"event_data.DeviceName\",\"type\":\"string\",\"count\":0,\"scripted\":false,\"searchable\":true,\"aggregatable\":true,\"readFromDocValues\":true},{\"name\":\"event_data.DeviceNameLength\",\"type\":\"string\",\"count\":0,\"scripted\":false,\"searchable\":true,\"aggregatable\":true,\"readFromDocValues\":true},{\"name\":\"event_data.DeviceTime\",\"type\":\"string\",\"count\":0,\"scripted\":false,\"searchable\":true,\"aggregatable\":true,\"readFromDocValues\":true},{\"name\":\"event_data.DeviceVersionMajor\",\"type\":\"string\",\"count\":0,\"scripted\":false,\"searchable\":true,\"aggregatable\":true,\"readFromDocValues\":true},{\"name\":\"event_data.DeviceVersionMinor\",\"type\":\"string\",\"count\":0,\"scripted\":false,\"searchable\":true,\"aggregatable\":true,\"readFromDocValues\":true},{\"name\":\"event_data.DirtyPages\",\"type\":\"string\",\"count\":0,\"scripted\":false,\"searchable\":true,\"aggregatable\":true,\"readFromDocValues\":true},{\"name\":\"event_data.DisableIntegrityChecks\",\"type\":\"string\",\"count\":0,\"scripted\":false,\"searchable\":true,\"aggregatable\":true,\"readFromDocValues\":true},{\"name\":\"event_data.DisplayName\",\"type\":\"string\",\"count\":0,\"scripted\":false,\"searchable\":true,\"aggregatable\":true,\"readFromDocValues\":true},{\"name\":\"event_data.DnsServerList\",\"type\":\"string\",\"count\":0,\"scripted\":false,\"searchable\":true,\"aggregatable\":true,\"readFromDocValues\":true},{\"name\":\"event_data.DomainName\",\"type\":\"string\",\"count\":0,\"scripted\":false,\"searchable\":true,\"aggregatable\":true,\"readFromDocValues\":true},{\"name\":\"event_data.DomainPeer\",\"type\":\"string\",\"count\":0,\"scripted\":false,\"searchable\":true,\"aggregatable\":true,\"readFromDocValues\":true},{\"name\":\"event_data.DriveName\",\"type\":\"string\",\"count\":0,\"scripted\":false,\"searchable\":true,\"aggregatable\":true,\"readFromDocValues\":true},{\"name\":\"event_data.DriverInitDuration\",\"type\":\"string\",\"count\":0,\"scripted\":false,\"searchable\":true,\"aggregatable\":true,\"readFromDocValues\":true},{\"name\":\"event_data.DriverName\",\"type\":\"string\",\"count\":0,\"scripted\":false,\"searchable\":true,\"aggregatable\":true,\"readFromDocValues\":true},{\"name\":\"event_data.DriverNameLength\",\"type\":\"string\",\"count\":0,\"scripted\":false,\"searchable\":true,\"aggregatable\":true,\"readFromDocValues\":true},{\"name\":\"event_data.Dummy\",\"type\":\"string\",\"count\":0,\"scripted\":false,\"searchable\":true,\"aggregatable\":true,\"readFromDocValues\":true},{\"name\":\"event_data.DwordVal\",\"type\":\"string\",\"count\":0,\"scripted\":false,\"searchable\":true,\"aggregatable\":true,\"readFromDocValues\":true},{\"name\":\"event_data.EffectiveState\",\"type\":\"string\",\"count\":0,\"scripted\":false,\"searchable\":true,\"aggregatable\":true,\"readFromDocValues\":true},{\"name\":\"event_data.ElevatedToken\",\"type\":\"string\",\"count\":0,\"scripted\":false,\"searchable\":true,\"aggregatable\":true,\"readFromDocValues\":true},{\"name\":\"event_data.EnableDisableReason\",\"type\":\"string\",\"count\":0,\"scripted\":false,\"searchable\":true,\"aggregatable\":true,\"readFromDocValues\":true},{\"name\":\"event_data.EntryCount\",\"type\":\"string\",\"count\":0,\"scripted\":false,\"searchable\":true,\"aggregatable\":true,\"readFromDocValues\":true},{\"name\":\"event_data.ErrorBatteryCount\",\"type\":\"string\",\"count\":0,\"scripted\":false,\"searchable\":true,\"aggregatable\":true,\"readFromDocValues\":true},{\"name\":\"event_data.ErrorCode\",\"type\":\"string\",\"count\":0,\"scripted\":false,\"searchable\":true,\"aggregatable\":true,\"readFromDocValues\":true},{\"name\":\"event_data.ErrorDescription\",\"type\":\"string\",\"count\":0,\"scripted\":false,\"searchable\":true,\"aggregatable\":true,\"readFromDocValues\":true},{\"name\":\"event_data.ErrorMessage\",\"type\":\"string\",\"count\":0,\"scripted\":false,\"searchable\":true,\"aggregatable\":true,\"readFromDocValues\":true},{\"name\":\"event_data.EventSourceId\",\"type\":\"string\",\"count\":0,\"scripted\":false,\"searchable\":true,\"aggregatable\":true,\"readFromDocValues\":true},{\"name\":\"event_data.ExitBootServicesEntry\",\"type\":\"string\",\"count\":0,\"scripted\":false,\"searchable\":true,\"aggregatable\":true,\"readFromDocValues\":true},{\"name\":\"event_data.ExitBootServicesExit\",\"type\":\"string\",\"count\":0,\"scripted\":false,\"searchable\":true,\"aggregatable\":true,\"readFromDocValues\":true},{\"name\":\"event_data.ExtensionId\",\"type\":\"string\",\"count\":0,\"scripted\":false,\"searchable\":true,\"aggregatable\":true,\"readFromDocValues\":true},{\"name\":\"event_data.ExtensionName\",\"type\":\"string\",\"count\":0,\"scripted\":false,\"searchable\":true,\"aggregatable\":true,\"readFromDocValues\":true},{\"name\":\"event_data.ExtraInfo\",\"type\":\"string\",\"count\":0,\"scripted\":false,\"searchable\":true,\"aggregatable\":true,\"readFromDocValues\":true},{\"name\":\"event_data.ExtraInfoLength\",\"type\":\"string\",\"count\":0,\"scripted\":false,\"searchable\":true,\"aggregatable\":true,\"readFromDocValues\":true},{\"name\":\"event_data.ExtraInfoString\",\"type\":\"string\",\"count\":0,\"scripted\":false,\"searchable\":true,\"aggregatable\":true,\"readFromDocValues\":true},{\"name\":\"event_data.ExtraString\",\"type\":\"string\",\"count\":0,\"scripted\":false,\"searchable\":true,\"aggregatable\":true,\"readFromDocValues\":true},{\"name\":\"event_data.ExtraStringLength\",\"type\":\"string\",\"count\":0,\"scripted\":false,\"searchable\":true,\"aggregatable\":true,\"readFromDocValues\":true},{\"name\":\"event_data.FailureMsgId\",\"type\":\"string\",\"count\":0,\"scripted\":false,\"searchable\":true,\"aggregatable\":true,\"readFromDocValues\":true},{\"name\":\"event_data.FailureName\",\"type\":\"string\",\"count\":0,\"scripted\":false,\"searchable\":true,\"aggregatable\":true,\"readFromDocValues\":true},{\"name\":\"event_data.FailureNameLength\",\"type\":\"string\",\"count\":0,\"scripted\":false,\"searchable\":true,\"aggregatable\":true,\"readFromDocValues\":true},{\"name\":\"event_data.FailureStatus\",\"type\":\"string\",\"count\":0,\"scripted\":false,\"searchable\":true,\"aggregatable\":true,\"readFromDocValues\":true},{\"name\":\"event_data.FilePath\",\"type\":\"string\",\"count\":0,\"scripted\":false,\"searchable\":true,\"aggregatable\":true,\"readFromDocValues\":true},{\"name\":\"event_data.FilesCachedFirstPass\",\"type\":\"string\",\"count\":0,\"scripted\":false,\"searchable\":true,\"aggregatable\":true,\"readFromDocValues\":true},{\"name\":\"event_data.FilesMissedSecondPass\",\"type\":\"string\",\"count\":0,\"scripted\":false,\"searchable\":true,\"aggregatable\":true,\"readFromDocValues\":true},{\"name\":\"event_data.FilesResident\",\"type\":\"string\",\"count\":0,\"scripted\":false,\"searchable\":true,\"aggregatable\":true,\"readFromDocValues\":true},{\"name\":\"event_data.FilesScoped\",\"type\":\"string\",\"count\":0,\"scripted\":false,\"searchable\":true,\"aggregatable\":true,\"readFromDocValues\":true},{\"name\":\"event_data.FilterHostProcessID\",\"type\":\"string\",\"count\":0,\"scripted\":false,\"searchable\":true,\"aggregatable\":true,\"readFromDocValues\":true},{\"name\":\"event_data.FilterID\",\"type\":\"string\",\"count\":0,\"scripted\":false,\"searchable\":true,\"aggregatable\":true,\"readFromDocValues\":true},{\"name\":\"event_data.FinalStatus\",\"type\":\"string\",\"count\":0,\"scripted\":false,\"searchable\":true,\"aggregatable\":true,\"readFromDocValues\":true},{\"name\":\"event_data.Flags\",\"type\":\"string\",\"count\":0,\"scripted\":false,\"searchable\":true,\"aggregatable\":true,\"readFromDocValues\":true},{\"name\":\"event_data.FlightSigning\",\"type\":\"string\",\"count\":0,\"scripted\":false,\"searchable\":true,\"aggregatable\":true,\"readFromDocValues\":true},{\"name\":\"event_data.FullResume\",\"type\":\"string\",\"count\":0,\"scripted\":false,\"searchable\":true,\"aggregatable\":true,\"readFromDocValues\":true},{\"name\":\"event_data.GPOCNName\",\"type\":\"string\",\"count\":0,\"scripted\":false,\"searchable\":true,\"aggregatable\":true,\"readFromDocValues\":true},{\"name\":\"event_data.GPODisplayName\",\"type\":\"string\",\"count\":0,\"scripted\":false,\"searchable\":true,\"aggregatable\":true,\"readFromDocValues\":true},{\"name\":\"event_data.GPOFileSystemPath\",\"type\":\"string\",\"count\":0,\"scripted\":false,\"searchable\":true,\"aggregatable\":true,\"readFromDocValues\":true},{\"name\":\"event_data.GPOScriptCommandString\",\"type\":\"string\",\"count\":0,\"scripted\":false,\"searchable\":true,\"aggregatable\":true,\"readFromDocValues\":true},{\"name\":\"event_data.Group\",\"type\":\"string\",\"count\":0,\"scripted\":false,\"searchable\":true,\"aggregatable\":true,\"readFromDocValues\":true},{\"name\":\"event_data.HandleId\",\"type\":\"string\",\"count\":0,\"scripted\":false,\"searchable\":true,\"aggregatable\":true,\"readFromDocValues\":true},{\"name\":\"event_data.HiberPagesWritten\",\"type\":\"string\",\"count\":0,\"scripted\":false,\"searchable\":true,\"aggregatable\":true,\"readFromDocValues\":true},{\"name\":\"event_data.HiberReadDuration\",\"type\":\"string\",\"count\":0,\"scripted\":false,\"searchable\":true,\"aggregatable\":true,\"readFromDocValues\":true},{\"name\":\"event_data.HiberWriteDuration\",\"type\":\"string\",\"count\":0,\"scripted\":false,\"searchable\":true,\"aggregatable\":true,\"readFromDocValues\":true},{\"name\":\"event_data.HiveName\",\"type\":\"string\",\"count\":0,\"scripted\":false,\"searchable\":true,\"aggregatable\":true,\"readFromDocValues\":true},{\"name\":\"event_data.HiveNameLength\",\"type\":\"string\",\"count\":0,\"scripted\":false,\"searchable\":true,\"aggregatable\":true,\"readFromDocValues\":true},{\"name\":\"event_data.HomeDirectory\",\"type\":\"string\",\"count\":0,\"scripted\":false,\"searchable\":true,\"aggregatable\":true,\"readFromDocValues\":true},{\"name\":\"event_data.HomePath\",\"type\":\"string\",\"count\":0,\"scripted\":false,\"searchable\":true,\"aggregatable\":true,\"readFromDocValues\":true},{\"name\":\"event_data.HostName\",\"type\":\"string\",\"count\":0,\"scripted\":false,\"searchable\":true,\"aggregatable\":true,\"readFromDocValues\":true},{\"name\":\"event_data.HostOSName\",\"type\":\"string\",\"count\":0,\"scripted\":false,\"searchable\":true,\"aggregatable\":true,\"readFromDocValues\":true},{\"name\":\"event_data.HostOSbuildversion\",\"type\":\"string\",\"count\":0,\"scripted\":false,\"searchable\":true,\"aggregatable\":true,\"readFromDocValues\":true},{\"name\":\"event_data.HostOSmajorversion\",\"type\":\"string\",\"count\":0,\"scripted\":false,\"searchable\":true,\"aggregatable\":true,\"readFromDocValues\":true},{\"name\":\"event_data.HostOSminorversion\",\"type\":\"string\",\"count\":0,\"scripted\":false,\"searchable\":true,\"aggregatable\":true,\"readFromDocValues\":true},{\"name\":\"event_data.HostOSservicepackmajorversion\",\"type\":\"string\",\"count\":0,\"scripted\":false,\"searchable\":true,\"aggregatable\":true,\"readFromDocValues\":true},{\"name\":\"event_data.HostOSservicepackminorversion\",\"type\":\"string\",\"count\":0,\"scripted\":false,\"searchable\":true,\"aggregatable\":true,\"readFromDocValues\":true},{\"name\":\"event_data.HostOSwasWindowsPE\",\"type\":\"string\",\"count\":0,\"scripted\":false,\"searchable\":true,\"aggregatable\":true,\"readFromDocValues\":true},{\"name\":\"event_data.HypervisorDebug\",\"type\":\"string\",\"count\":0,\"scripted\":false,\"searchable\":true,\"aggregatable\":true,\"readFromDocValues\":true},{\"name\":\"event_data.HypervisorLaunchType\",\"type\":\"string\",\"count\":0,\"scripted\":false,\"searchable\":true,\"aggregatable\":true,\"readFromDocValues\":true},{\"name\":\"event_data.HypervisorLoadOptions\",\"type\":\"string\",\"count\":0,\"scripted\":false,\"searchable\":true,\"aggregatable\":true,\"readFromDocValues\":true},{\"name\":\"event_data.IdleImplementation\",\"type\":\"string\",\"count\":0,\"scripted\":false,\"searchable\":true,\"aggregatable\":true,\"readFromDocValues\":true},{\"name\":\"event_data.IdleStateCount\",\"type\":\"string\",\"count\":0,\"scripted\":false,\"searchable\":true,\"aggregatable\":true,\"readFromDocValues\":true},{\"name\":\"event_data.ImagePath\",\"type\":\"string\",\"count\":0,\"scripted\":false,\"searchable\":true,\"aggregatable\":true,\"readFromDocValues\":true},{\"name\":\"event_data.ImpersonationLevel\",\"type\":\"string\",\"count\":0,\"scripted\":false,\"searchable\":true,\"aggregatable\":true,\"readFromDocValues\":true},{\"name\":\"event_data.Installwasanupgrade\",\"type\":\"string\",\"count\":0,\"scripted\":false,\"searchable\":true,\"aggregatable\":true,\"readFromDocValues\":true},{\"name\":\"event_data.InstanceName\",\"type\":\"string\",\"count\":0,\"scripted\":false,\"searchable\":true,\"aggregatable\":true,\"readFromDocValues\":true},{\"name\":\"event_data.InstanceNameLength\",\"type\":\"string\",\"count\":0,\"scripted\":false,\"searchable\":true,\"aggregatable\":true,\"readFromDocValues\":true},{\"name\":\"event_data.InternalCode\",\"type\":\"string\",\"count\":0,\"scripted\":false,\"searchable\":true,\"aggregatable\":true,\"readFromDocValues\":true},{\"name\":\"event_data.IpAddress\",\"type\":\"string\",\"count\":0,\"scripted\":false,\"searchable\":true,\"aggregatable\":true,\"readFromDocValues\":true},{\"name\":\"event_data.IpPort\",\"type\":\"string\",\"count\":0,\"scripted\":false,\"searchable\":true,\"aggregatable\":true,\"readFromDocValues\":true},{\"name\":\"event_data.Ipaddress\",\"type\":\"string\",\"count\":0,\"scripted\":false,\"searchable\":true,\"aggregatable\":true,\"readFromDocValues\":true},{\"name\":\"event_data.IsTestConfig\",\"type\":\"string\",\"count\":0,\"scripted\":false,\"searchable\":true,\"aggregatable\":true,\"readFromDocValues\":true},{\"name\":\"event_data.KernelDebug\",\"type\":\"string\",\"count\":0,\"scripted\":false,\"searchable\":true,\"aggregatable\":true,\"readFromDocValues\":true},{\"name\":\"event_data.KeyLength\",\"type\":\"string\",\"count\":0,\"scripted\":false,\"searchable\":true,\"aggregatable\":true,\"readFromDocValues\":true},{\"name\":\"event_data.KeyName\",\"type\":\"string\",\"count\":0,\"scripted\":false,\"searchable\":true,\"aggregatable\":true,\"readFromDocValues\":true},{\"name\":\"event_data.KeyType\",\"type\":\"string\",\"count\":0,\"scripted\":false,\"searchable\":true,\"aggregatable\":true,\"readFromDocValues\":true},{\"name\":\"event_data.KeysUpdated\",\"type\":\"string\",\"count\":0,\"scripted\":false,\"searchable\":true,\"aggregatable\":true,\"readFromDocValues\":true},{\"name\":\"event_data.LastBootGood\",\"type\":\"string\",\"count\":0,\"scripted\":false,\"searchable\":true,\"aggregatable\":true,\"readFromDocValues\":true},{\"name\":\"event_data.LastBootId\",\"type\":\"string\",\"count\":0,\"scripted\":false,\"searchable\":true,\"aggregatable\":true,\"readFromDocValues\":true},{\"name\":\"event_data.LastShutdownGood\",\"type\":\"string\",\"count\":0,\"scripted\":false,\"searchable\":true,\"aggregatable\":true,\"readFromDocValues\":true},{\"name\":\"event_data.LmPackageName\",\"type\":\"string\",\"count\":0,\"scripted\":false,\"searchable\":true,\"aggregatable\":true,\"readFromDocValues\":true},{\"name\":\"event_data.LoadOSImageStart\",\"type\":\"string\",\"count\":0,\"scripted\":false,\"searchable\":true,\"aggregatable\":true,\"readFromDocValues\":true},{\"name\":\"event_data.LoadOptions\",\"type\":\"string\",\"count\":0,\"scripted\":false,\"searchable\":true,\"aggregatable\":true,\"readFromDocValues\":true},{\"name\":\"event_data.LogonGuid\",\"type\":\"string\",\"count\":0,\"scripted\":false,\"searchable\":true,\"aggregatable\":true,\"readFromDocValues\":true},{\"name\":\"event_data.LogonHours\",\"type\":\"string\",\"count\":0,\"scripted\":false,\"searchable\":true,\"aggregatable\":true,\"readFromDocValues\":true},{\"name\":\"event_data.LogonProcessName\",\"type\":\"string\",\"count\":0,\"scripted\":false,\"searchable\":true,\"aggregatable\":true,\"readFromDocValues\":true},{\"name\":\"event_data.LogonType\",\"type\":\"string\",\"count\":0,\"scripted\":false,\"searchable\":true,\"aggregatable\":true,\"readFromDocValues\":true},{\"name\":\"event_data.MajorVersion\",\"type\":\"string\",\"count\":0,\"scripted\":false,\"searchable\":true,\"aggregatable\":true,\"readFromDocValues\":true},{\"name\":\"event_data.MandatoryLabel\",\"type\":\"string\",\"count\":0,\"scripted\":false,\"searchable\":true,\"aggregatable\":true,\"readFromDocValues\":true},{\"name\":\"event_data.MaximumPerformancePercent\",\"type\":\"string\",\"count\":0,\"scripted\":false,\"searchable\":true,\"aggregatable\":true,\"readFromDocValues\":true},{\"name\":\"event_data.MemberName\",\"type\":\"string\",\"count\":0,\"scripted\":false,\"searchable\":true,\"aggregatable\":true,\"readFromDocValues\":true},{\"name\":\"event_data.MemberSid\",\"type\":\"string\",\"count\":0,\"scripted\":false,\"searchable\":true,\"aggregatable\":true,\"readFromDocValues\":true},{\"name\":\"event_data.MinimumPerformancePercent\",\"type\":\"string\",\"count\":0,\"scripted\":false,\"searchable\":true,\"aggregatable\":true,\"readFromDocValues\":true},{\"name\":\"event_data.MinimumThrottlePercent\",\"type\":\"string\",\"count\":0,\"scripted\":false,\"searchable\":true,\"aggregatable\":true,\"readFromDocValues\":true},{\"name\":\"event_data.MinorVersion\",\"type\":\"string\",\"count\":0,\"scripted\":false,\"searchable\":true,\"aggregatable\":true,\"readFromDocValues\":true},{\"name\":\"event_data.NTSTATUS\",\"type\":\"string\",\"count\":0,\"scripted\":false,\"searchable\":true,\"aggregatable\":true,\"readFromDocValues\":true},{\"name\":\"event_data.NetStatusCode\",\"type\":\"string\",\"count\":0,\"scripted\":false,\"searchable\":true,\"aggregatable\":true,\"readFromDocValues\":true},{\"name\":\"event_data.NewProcessBareName\",\"type\":\"string\",\"count\":0,\"scripted\":false,\"searchable\":true,\"aggregatable\":true,\"readFromDocValues\":true},{\"name\":\"event_data.NewProcessId\",\"type\":\"string\",\"count\":0,\"scripted\":false,\"searchable\":true,\"aggregatable\":true,\"readFromDocValues\":true},{\"name\":\"event_data.NewProcessName\",\"type\":\"string\",\"count\":0,\"scripted\":false,\"searchable\":true,\"aggregatable\":true,\"readFromDocValues\":true},{\"name\":\"event_data.NewProcessSeverity\",\"type\":\"string\",\"count\":1,\"scripted\":false,\"searchable\":true,\"aggregatable\":true,\"readFromDocValues\":true},{\"name\":\"event_data.NewProcessSeverityComment\",\"type\":\"string\",\"count\":0,\"scripted\":false,\"searchable\":true,\"aggregatable\":true,\"readFromDocValues\":true},{\"name\":\"event_data.NewSchemeGuid\",\"type\":\"string\",\"count\":0,\"scripted\":false,\"searchable\":true,\"aggregatable\":true,\"readFromDocValues\":true},{\"name\":\"event_data.NewSd\",\"type\":\"string\",\"count\":0,\"scripted\":false,\"searchable\":true,\"aggregatable\":true,\"readFromDocValues\":true},{\"name\":\"event_data.NewSize\",\"type\":\"string\",\"count\":0,\"scripted\":false,\"searchable\":true,\"aggregatable\":true,\"readFromDocValues\":true},{\"name\":\"event_data.NewTime\",\"type\":\"string\",\"count\":0,\"scripted\":false,\"searchable\":true,\"aggregatable\":true,\"readFromDocValues\":true},{\"name\":\"event_data.NewUacValue\",\"type\":\"string\",\"count\":0,\"scripted\":false,\"searchable\":true,\"aggregatable\":true,\"readFromDocValues\":true},{\"name\":\"event_data.NoMultiStageResumeReason\",\"type\":\"string\",\"count\":0,\"scripted\":false,\"searchable\":true,\"aggregatable\":true,\"readFromDocValues\":true},{\"name\":\"event_data.NominalFrequency\",\"type\":\"string\",\"count\":0,\"scripted\":false,\"searchable\":true,\"aggregatable\":true,\"readFromDocValues\":true},{\"name\":\"event_data.NotificationPackageName\",\"type\":\"string\",\"count\":0,\"scripted\":false,\"searchable\":true,\"aggregatable\":true,\"readFromDocValues\":true},{\"name\":\"event_data.Number\",\"type\":\"string\",\"count\":0,\"scripted\":false,\"searchable\":true,\"aggregatable\":true,\"readFromDocValues\":true},{\"name\":\"event_data.NumberOfGroupPolicyObjects\",\"type\":\"string\",\"count\":0,\"scripted\":false,\"searchable\":true,\"aggregatable\":true,\"readFromDocValues\":true},{\"name\":\"event_data.OSEditionID\",\"type\":\"string\",\"count\":0,\"scripted\":false,\"searchable\":true,\"aggregatable\":true,\"readFromDocValues\":true},{\"name\":\"event_data.OSName\",\"type\":\"string\",\"count\":0,\"scripted\":false,\"searchable\":true,\"aggregatable\":true,\"readFromDocValues\":true},{\"name\":\"event_data.OSbuildversion\",\"type\":\"string\",\"count\":0,\"scripted\":false,\"searchable\":true,\"aggregatable\":true,\"readFromDocValues\":true},{\"name\":\"event_data.OSmajorversion\",\"type\":\"string\",\"count\":0,\"scripted\":false,\"searchable\":true,\"aggregatable\":true,\"readFromDocValues\":true},{\"name\":\"event_data.OSminorversion\",\"type\":\"string\",\"count\":0,\"scripted\":false,\"searchable\":true,\"aggregatable\":true,\"readFromDocValues\":true},{\"name\":\"event_data.OSservicepackmajorversion\",\"type\":\"string\",\"count\":0,\"scripted\":false,\"searchable\":true,\"aggregatable\":true,\"readFromDocValues\":true},{\"name\":\"event_data.OSservicepackminorversion\",\"type\":\"string\",\"count\":0,\"scripted\":false,\"searchable\":true,\"aggregatable\":true,\"readFromDocValues\":true},{\"name\":\"event_data.ObjectName\",\"type\":\"string\",\"count\":0,\"scripted\":false,\"searchable\":true,\"aggregatable\":true,\"readFromDocValues\":true},{\"name\":\"event_data.ObjectServer\",\"type\":\"string\",\"count\":0,\"scripted\":false,\"searchable\":true,\"aggregatable\":true,\"readFromDocValues\":true},{\"name\":\"event_data.ObjectType\",\"type\":\"string\",\"count\":0,\"scripted\":false,\"searchable\":true,\"aggregatable\":true,\"readFromDocValues\":true},{\"name\":\"event_data.OldSchemeGuid\",\"type\":\"string\",\"count\":0,\"scripted\":false,\"searchable\":true,\"aggregatable\":true,\"readFromDocValues\":true},{\"name\":\"event_data.OldSd\",\"type\":\"string\",\"count\":0,\"scripted\":false,\"searchable\":true,\"aggregatable\":true,\"readFromDocValues\":true},{\"name\":\"event_data.OldTime\",\"type\":\"string\",\"count\":0,\"scripted\":false,\"searchable\":true,\"aggregatable\":true,\"readFromDocValues\":true},{\"name\":\"event_data.OldUacValue\",\"type\":\"string\",\"count\":0,\"scripted\":false,\"searchable\":true,\"aggregatable\":true,\"readFromDocValues\":true},{\"name\":\"event_data.Operation\",\"type\":\"string\",\"count\":0,\"scripted\":false,\"searchable\":true,\"aggregatable\":true,\"readFromDocValues\":true},{\"name\":\"event_data.OriginalSize\",\"type\":\"string\",\"count\":0,\"scripted\":false,\"searchable\":true,\"aggregatable\":true,\"readFromDocValues\":true},{\"name\":\"event_data.ParentProcessName\",\"type\":\"string\",\"count\":0,\"scripted\":false,\"searchable\":true,\"aggregatable\":true,\"readFromDocValues\":true},{\"name\":\"event_data.PasswordLastSet\",\"type\":\"string\",\"count\":0,\"scripted\":false,\"searchable\":true,\"aggregatable\":true,\"readFromDocValues\":true},{\"name\":\"event_data.PccChanges\",\"type\":\"string\",\"count\":0,\"scripted\":false,\"searchable\":true,\"aggregatable\":true,\"readFromDocValues\":true},{\"name\":\"event_data.PerformanceImplementation\",\"type\":\"string\",\"count\":0,\"scripted\":false,\"searchable\":true,\"aggregatable\":true,\"readFromDocValues\":true},{\"name\":\"event_data.PowerButtonTimestamp\",\"type\":\"string\",\"count\":0,\"scripted\":false,\"searchable\":true,\"aggregatable\":true,\"readFromDocValues\":true},{\"name\":\"event_data.PpcChanges\",\"type\":\"string\",\"count\":0,\"scripted\":false,\"searchable\":true,\"aggregatable\":true,\"readFromDocValues\":true},{\"name\":\"event_data.PreviousTime\",\"type\":\"string\",\"count\":0,\"scripted\":false,\"searchable\":true,\"aggregatable\":true,\"readFromDocValues\":true},{\"name\":\"event_data.PrimaryGroupId\",\"type\":\"string\",\"count\":0,\"scripted\":false,\"searchable\":true,\"aggregatable\":true,\"readFromDocValues\":true},{\"name\":\"event_data.PrivilegeList\",\"type\":\"string\",\"count\":0,\"scripted\":false,\"searchable\":true,\"aggregatable\":true,\"readFromDocValues\":true},{\"name\":\"event_data.ProcessId\",\"type\":\"string\",\"count\":0,\"scripted\":false,\"searchable\":true,\"aggregatable\":true,\"readFromDocValues\":true},{\"name\":\"event_data.ProcessName\",\"type\":\"string\",\"count\":0,\"scripted\":false,\"searchable\":true,\"aggregatable\":true,\"readFromDocValues\":true},{\"name\":\"event_data.ProcessNameLength\",\"type\":\"string\",\"count\":0,\"scripted\":false,\"searchable\":true,\"aggregatable\":true,\"readFromDocValues\":true},{\"name\":\"event_data.ProcessPath\",\"type\":\"string\",\"count\":0,\"scripted\":false,\"searchable\":true,\"aggregatable\":true,\"readFromDocValues\":true},{\"name\":\"event_data.ProcessPid\",\"type\":\"string\",\"count\":0,\"scripted\":false,\"searchable\":true,\"aggregatable\":true,\"readFromDocValues\":true},{\"name\":\"event_data.ProcessingMode\",\"type\":\"string\",\"count\":0,\"scripted\":false,\"searchable\":true,\"aggregatable\":true,\"readFromDocValues\":true},{\"name\":\"event_data.ProcessingTimeInMilliseconds\",\"type\":\"string\",\"count\":0,\"scripted\":false,\"searchable\":true,\"aggregatable\":true,\"readFromDocValues\":true},{\"name\":\"event_data.ProfilePath\",\"type\":\"string\",\"count\":0,\"scripted\":false,\"searchable\":true,\"aggregatable\":true,\"readFromDocValues\":true},{\"name\":\"event_data.ProgrammedWakeTimeAc\",\"type\":\"string\",\"count\":0,\"scripted\":false,\"searchable\":true,\"aggregatable\":true,\"readFromDocValues\":true},{\"name\":\"event_data.ProgrammedWakeTimeDc\",\"type\":\"string\",\"count\":0,\"scripted\":false,\"searchable\":true,\"aggregatable\":true,\"readFromDocValues\":true},{\"name\":\"event_data.ProtocolHostProcessID\",\"type\":\"string\",\"count\":0,\"scripted\":false,\"searchable\":true,\"aggregatable\":true,\"readFromDocValues\":true},{\"name\":\"event_data.ProviderName\",\"type\":\"string\",\"count\":0,\"scripted\":false,\"searchable\":true,\"aggregatable\":true,\"readFromDocValues\":true},{\"name\":\"event_data.PuaCount\",\"type\":\"string\",\"count\":0,\"scripted\":false,\"searchable\":true,\"aggregatable\":true,\"readFromDocValues\":true},{\"name\":\"event_data.PuaPolicyId\",\"type\":\"string\",\"count\":0,\"scripted\":false,\"searchable\":true,\"aggregatable\":true,\"readFromDocValues\":true},{\"name\":\"event_data.QfeVersion\",\"type\":\"string\",\"count\":0,\"scripted\":false,\"searchable\":true,\"aggregatable\":true,\"readFromDocValues\":true},{\"name\":\"event_data.QueryName\",\"type\":\"string\",\"count\":0,\"scripted\":false,\"searchable\":true,\"aggregatable\":true,\"readFromDocValues\":true},{\"name\":\"event_data.Reason\",\"type\":\"string\",\"count\":0,\"scripted\":false,\"searchable\":true,\"aggregatable\":true,\"readFromDocValues\":true},{\"name\":\"event_data.RemoteAddress\",\"type\":\"string\",\"count\":0,\"scripted\":false,\"searchable\":true,\"aggregatable\":true,\"readFromDocValues\":true},{\"name\":\"event_data.RemoteEventLogging\",\"type\":\"string\",\"count\":0,\"scripted\":false,\"searchable\":true,\"aggregatable\":true,\"readFromDocValues\":true},{\"name\":\"event_data.ResetEndStart\",\"type\":\"string\",\"count\":0,\"scripted\":false,\"searchable\":true,\"aggregatable\":true,\"readFromDocValues\":true},{\"name\":\"event_data.RestrictedAdminMode\",\"type\":\"string\",\"count\":0,\"scripted\":false,\"searchable\":true,\"aggregatable\":true,\"readFromDocValues\":true},{\"name\":\"event_data.ResumeCount\",\"type\":\"string\",\"count\":0,\"scripted\":false,\"searchable\":true,\"aggregatable\":true,\"readFromDocValues\":true},{\"name\":\"event_data.RetryMinutes\",\"type\":\"string\",\"count\":0,\"scripted\":false,\"searchable\":true,\"aggregatable\":true,\"readFromDocValues\":true},{\"name\":\"event_data.ReturnCode\",\"type\":\"string\",\"count\":0,\"scripted\":false,\"searchable\":true,\"aggregatable\":true,\"readFromDocValues\":true},{\"name\":\"event_data.RmId\",\"type\":\"string\",\"count\":0,\"scripted\":false,\"searchable\":true,\"aggregatable\":true,\"readFromDocValues\":true},{\"name\":\"event_data.SPI\",\"type\":\"string\",\"count\":0,\"scripted\":false,\"searchable\":true,\"aggregatable\":true,\"readFromDocValues\":true},{\"name\":\"event_data.SamAccountName\",\"type\":\"string\",\"count\":0,\"scripted\":false,\"searchable\":true,\"aggregatable\":true,\"readFromDocValues\":true},{\"name\":\"event_data.ScriptPath\",\"type\":\"string\",\"count\":0,\"scripted\":false,\"searchable\":true,\"aggregatable\":true,\"readFromDocValues\":true},{\"name\":\"event_data.ScriptType\",\"type\":\"string\",\"count\":0,\"scripted\":false,\"searchable\":true,\"aggregatable\":true,\"readFromDocValues\":true},{\"name\":\"event_data.SecurityPackageName\",\"type\":\"string\",\"count\":0,\"scripted\":false,\"searchable\":true,\"aggregatable\":true,\"readFromDocValues\":true},{\"name\":\"event_data.Sent UpdateServer\",\"type\":\"string\",\"count\":0,\"scripted\":false,\"searchable\":true,\"aggregatable\":true,\"readFromDocValues\":true},{\"name\":\"event_data.ServiceAccount\",\"type\":\"string\",\"count\":1,\"scripted\":false,\"searchable\":true,\"aggregatable\":true,\"readFromDocValues\":true},{\"name\":\"event_data.ServiceFileName\",\"type\":\"string\",\"count\":0,\"scripted\":false,\"searchable\":true,\"aggregatable\":true,\"readFromDocValues\":true},{\"name\":\"event_data.ServiceName\",\"type\":\"string\",\"count\":1,\"scripted\":false,\"searchable\":true,\"aggregatable\":true,\"readFromDocValues\":true},{\"name\":\"event_data.ServiceStartType\",\"type\":\"string\",\"count\":0,\"scripted\":false,\"searchable\":true,\"aggregatable\":true,\"readFromDocValues\":true},{\"name\":\"event_data.ServiceType\",\"type\":\"string\",\"count\":0,\"scripted\":false,\"searchable\":true,\"aggregatable\":true,\"readFromDocValues\":true},{\"name\":\"event_data.ServiceVersion\",\"type\":\"string\",\"count\":0,\"scripted\":false,\"searchable\":true,\"aggregatable\":true,\"readFromDocValues\":true},{\"name\":\"event_data.ShutdownActionType\",\"type\":\"string\",\"count\":0,\"scripted\":false,\"searchable\":true,\"aggregatable\":true,\"readFromDocValues\":true},{\"name\":\"event_data.ShutdownEventCode\",\"type\":\"string\",\"count\":0,\"scripted\":false,\"searchable\":true,\"aggregatable\":true,\"readFromDocValues\":true},{\"name\":\"event_data.ShutdownReason\",\"type\":\"string\",\"count\":0,\"scripted\":false,\"searchable\":true,\"aggregatable\":true,\"readFromDocValues\":true},{\"name\":\"event_data.SidHistory\",\"type\":\"string\",\"count\":0,\"scripted\":false,\"searchable\":true,\"aggregatable\":true,\"readFromDocValues\":true},{\"name\":\"event_data.SleepDuration\",\"type\":\"string\",\"count\":0,\"scripted\":false,\"searchable\":true,\"aggregatable\":true,\"readFromDocValues\":true},{\"name\":\"event_data.SleepInProgress\",\"type\":\"string\",\"count\":0,\"scripted\":false,\"searchable\":true,\"aggregatable\":true,\"readFromDocValues\":true},{\"name\":\"event_data.SleepTime\",\"type\":\"string\",\"count\":0,\"scripted\":false,\"searchable\":true,\"aggregatable\":true,\"readFromDocValues\":true},{\"name\":\"event_data.SnapshotPath\",\"type\":\"string\",\"count\":0,\"scripted\":false,\"searchable\":true,\"aggregatable\":true,\"readFromDocValues\":true},{\"name\":\"event_data.SourceFileID\",\"type\":\"string\",\"count\":0,\"scripted\":false,\"searchable\":true,\"aggregatable\":true,\"readFromDocValues\":true},{\"name\":\"event_data.SourceLine\",\"type\":\"string\",\"count\":0,\"scripted\":false,\"searchable\":true,\"aggregatable\":true,\"readFromDocValues\":true},{\"name\":\"event_data.SourceTag\",\"type\":\"string\",\"count\":0,\"scripted\":false,\"searchable\":true,\"aggregatable\":true,\"readFromDocValues\":true},{\"name\":\"event_data.StartOSImageStart\",\"type\":\"string\",\"count\":0,\"scripted\":false,\"searchable\":true,\"aggregatable\":true,\"readFromDocValues\":true},{\"name\":\"event_data.StartTime\",\"type\":\"string\",\"count\":0,\"scripted\":false,\"searchable\":true,\"aggregatable\":true,\"readFromDocValues\":true},{\"name\":\"event_data.StartType\",\"type\":\"string\",\"count\":0,\"scripted\":false,\"searchable\":true,\"aggregatable\":true,\"readFromDocValues\":true},{\"name\":\"event_data.State\",\"type\":\"string\",\"count\":0,\"scripted\":false,\"searchable\":true,\"aggregatable\":true,\"readFromDocValues\":true},{\"name\":\"event_data.Status\",\"type\":\"string\",\"count\":0,\"scripted\":false,\"searchable\":true,\"aggregatable\":true,\"readFromDocValues\":true},{\"name\":\"event_data.StopTime\",\"type\":\"string\",\"count\":0,\"scripted\":false,\"searchable\":true,\"aggregatable\":true,\"readFromDocValues\":true},{\"name\":\"event_data.SubcategoryGuid\",\"type\":\"string\",\"count\":0,\"scripted\":false,\"searchable\":true,\"aggregatable\":true,\"readFromDocValues\":true},{\"name\":\"event_data.SubcategoryId\",\"type\":\"string\",\"count\":0,\"scripted\":false,\"searchable\":true,\"aggregatable\":true,\"readFromDocValues\":true},{\"name\":\"event_data.SubjectDomainName\",\"type\":\"string\",\"count\":0,\"scripted\":false,\"searchable\":true,\"aggregatable\":true,\"readFromDocValues\":true},{\"name\":\"event_data.SubjectLogonId\",\"type\":\"string\",\"count\":0,\"scripted\":false,\"searchable\":true,\"aggregatable\":true,\"readFromDocValues\":true},{\"name\":\"event_data.SubjectUserName\",\"type\":\"string\",\"count\":1,\"scripted\":false,\"searchable\":true,\"aggregatable\":true,\"readFromDocValues\":true},{\"name\":\"event_data.SubjectUserSid\",\"type\":\"string\",\"count\":0,\"scripted\":false,\"searchable\":true,\"aggregatable\":true,\"readFromDocValues\":true},{\"name\":\"event_data.SupportInfo1\",\"type\":\"string\",\"count\":0,\"scripted\":false,\"searchable\":true,\"aggregatable\":true,\"readFromDocValues\":true},{\"name\":\"event_data.SupportInfo2\",\"type\":\"string\",\"count\":0,\"scripted\":false,\"searchable\":true,\"aggregatable\":true,\"readFromDocValues\":true},{\"name\":\"event_data.SystemSleepTransitionsToOn\",\"type\":\"string\",\"count\":0,\"scripted\":false,\"searchable\":true,\"aggregatable\":true,\"readFromDocValues\":true},{\"name\":\"event_data.TSId\",\"type\":\"string\",\"count\":0,\"scripted\":false,\"searchable\":true,\"aggregatable\":true,\"readFromDocValues\":true},{\"name\":\"event_data.Target\",\"type\":\"string\",\"count\":0,\"scripted\":false,\"searchable\":true,\"aggregatable\":true,\"readFromDocValues\":true},{\"name\":\"event_data.TargetDomainName\",\"type\":\"string\",\"count\":0,\"scripted\":false,\"searchable\":true,\"aggregatable\":true,\"readFromDocValues\":true},{\"name\":\"event_data.TargetInfo\",\"type\":\"string\",\"count\":0,\"scripted\":false,\"searchable\":true,\"aggregatable\":true,\"readFromDocValues\":true},{\"name\":\"event_data.TargetLinkedLogonId\",\"type\":\"string\",\"count\":0,\"scripted\":false,\"searchable\":true,\"aggregatable\":true,\"readFromDocValues\":true},{\"name\":\"event_data.TargetLogonGuid\",\"type\":\"string\",\"count\":0,\"scripted\":false,\"searchable\":true,\"aggregatable\":true,\"readFromDocValues\":true},{\"name\":\"event_data.TargetLogonId\",\"type\":\"string\",\"count\":0,\"scripted\":false,\"searchable\":true,\"aggregatable\":true,\"readFromDocValues\":true},{\"name\":\"event_data.TargetOutboundDomainName\",\"type\":\"string\",\"count\":0,\"scripted\":false,\"searchable\":true,\"aggregatable\":true,\"readFromDocValues\":true},{\"name\":\"event_data.TargetOutboundUserName\",\"type\":\"string\",\"count\":0,\"scripted\":false,\"searchable\":true,\"aggregatable\":true,\"readFromDocValues\":true},{\"name\":\"event_data.TargetServerName\",\"type\":\"string\",\"count\":0,\"scripted\":false,\"searchable\":true,\"aggregatable\":true,\"readFromDocValues\":true},{\"name\":\"event_data.TargetSid\",\"type\":\"string\",\"count\":0,\"scripted\":false,\"searchable\":true,\"aggregatable\":true,\"readFromDocValues\":true},{\"name\":\"event_data.TargetState\",\"type\":\"string\",\"count\":0,\"scripted\":false,\"searchable\":true,\"aggregatable\":true,\"readFromDocValues\":true},{\"name\":\"event_data.TargetUserName\",\"type\":\"string\",\"count\":1,\"scripted\":false,\"searchable\":true,\"aggregatable\":true,\"readFromDocValues\":true},{\"name\":\"event_data.TargetUserSid\",\"type\":\"string\",\"count\":0,\"scripted\":false,\"searchable\":true,\"aggregatable\":true,\"readFromDocValues\":true},{\"name\":\"event_data.TestSigning\",\"type\":\"string\",\"count\":0,\"scripted\":false,\"searchable\":true,\"aggregatable\":true,\"readFromDocValues\":true},{\"name\":\"event_data.TimeProvider\",\"type\":\"string\",\"count\":0,\"scripted\":false,\"searchable\":true,\"aggregatable\":true,\"readFromDocValues\":true},{\"name\":\"event_data.TimeSource\",\"type\":\"string\",\"count\":0,\"scripted\":false,\"searchable\":true,\"aggregatable\":true,\"readFromDocValues\":true},{\"name\":\"event_data.TmId\",\"type\":\"string\",\"count\":0,\"scripted\":false,\"searchable\":true,\"aggregatable\":true,\"readFromDocValues\":true},{\"name\":\"event_data.TokenElevationType\",\"type\":\"string\",\"count\":0,\"scripted\":false,\"searchable\":true,\"aggregatable\":true,\"readFromDocValues\":true},{\"name\":\"event_data.TotalDirectories\",\"type\":\"string\",\"count\":0,\"scripted\":false,\"searchable\":true,\"aggregatable\":true,\"readFromDocValues\":true},{\"name\":\"event_data.TotalFiles\",\"type\":\"string\",\"count\":0,\"scripted\":false,\"searchable\":true,\"aggregatable\":true,\"readFromDocValues\":true},{\"name\":\"event_data.TpcChanges\",\"type\":\"string\",\"count\":0,\"scripted\":false,\"searchable\":true,\"aggregatable\":true,\"readFromDocValues\":true},{\"name\":\"event_data.TransitionsToOn\",\"type\":\"string\",\"count\":0,\"scripted\":false,\"searchable\":true,\"aggregatable\":true,\"readFromDocValues\":true},{\"name\":\"event_data.TransmittedServices\",\"type\":\"string\",\"count\":0,\"scripted\":false,\"searchable\":true,\"aggregatable\":true,\"readFromDocValues\":true},{\"name\":\"event_data.Turn\",\"type\":\"string\",\"count\":0,\"scripted\":false,\"searchable\":true,\"aggregatable\":true,\"readFromDocValues\":true},{\"name\":\"event_data.Url\",\"type\":\"string\",\"count\":0,\"scripted\":false,\"searchable\":true,\"aggregatable\":true,\"readFromDocValues\":true},{\"name\":\"event_data.UserAccountControl\",\"type\":\"string\",\"count\":0,\"scripted\":false,\"searchable\":true,\"aggregatable\":true,\"readFromDocValues\":true},{\"name\":\"event_data.UserParameters\",\"type\":\"string\",\"count\":0,\"scripted\":false,\"searchable\":true,\"aggregatable\":true,\"readFromDocValues\":true},{\"name\":\"event_data.UserPrincipalName\",\"type\":\"string\",\"count\":0,\"scripted\":false,\"searchable\":true,\"aggregatable\":true,\"readFromDocValues\":true},{\"name\":\"event_data.UserSid\",\"type\":\"string\",\"count\":0,\"scripted\":false,\"searchable\":true,\"aggregatable\":true,\"readFromDocValues\":true},{\"name\":\"event_data.UserWorkstations\",\"type\":\"string\",\"count\":0,\"scripted\":false,\"searchable\":true,\"aggregatable\":true,\"readFromDocValues\":true},{\"name\":\"event_data.ValidBatteryCount\",\"type\":\"string\",\"count\":0,\"scripted\":false,\"searchable\":true,\"aggregatable\":true,\"readFromDocValues\":true},{\"name\":\"event_data.Version\",\"type\":\"string\",\"count\":0,\"scripted\":false,\"searchable\":true,\"aggregatable\":true,\"readFromDocValues\":true},{\"name\":\"event_data.VirtualAccount\",\"type\":\"string\",\"count\":0,\"scripted\":false,\"searchable\":true,\"aggregatable\":true,\"readFromDocValues\":true},{\"name\":\"event_data.VolumeName\",\"type\":\"string\",\"count\":0,\"scripted\":false,\"searchable\":true,\"aggregatable\":true,\"readFromDocValues\":true},{\"name\":\"event_data.VsmLaunchType\",\"type\":\"string\",\"count\":0,\"scripted\":false,\"searchable\":true,\"aggregatable\":true,\"readFromDocValues\":true},{\"name\":\"event_data.VsmPolicy\",\"type\":\"string\",\"count\":0,\"scripted\":false,\"searchable\":true,\"aggregatable\":true,\"readFromDocValues\":true},{\"name\":\"event_data.WakeDuration\",\"type\":\"string\",\"count\":0,\"scripted\":false,\"searchable\":true,\"aggregatable\":true,\"readFromDocValues\":true},{\"name\":\"event_data.WakeFromState\",\"type\":\"string\",\"count\":0,\"scripted\":false,\"searchable\":true,\"aggregatable\":true,\"readFromDocValues\":true},{\"name\":\"event_data.WakeRequesterTypeAc\",\"type\":\"string\",\"count\":0,\"scripted\":false,\"searchable\":true,\"aggregatable\":true,\"readFromDocValues\":true},{\"name\":\"event_data.WakeRequesterTypeDc\",\"type\":\"string\",\"count\":0,\"scripted\":false,\"searchable\":true,\"aggregatable\":true,\"readFromDocValues\":true},{\"name\":\"event_data.WakeSourceTextLength\",\"type\":\"string\",\"count\":0,\"scripted\":false,\"searchable\":true,\"aggregatable\":true,\"readFromDocValues\":true},{\"name\":\"event_data.WakeSourceType\",\"type\":\"string\",\"count\":0,\"scripted\":false,\"searchable\":true,\"aggregatable\":true,\"readFromDocValues\":true},{\"name\":\"event_data.WakeTime\",\"type\":\"string\",\"count\":0,\"scripted\":false,\"searchable\":true,\"aggregatable\":true,\"readFromDocValues\":true},{\"name\":\"event_data.WakeTimerContextLength\",\"type\":\"string\",\"count\":0,\"scripted\":false,\"searchable\":true,\"aggregatable\":true,\"readFromDocValues\":true},{\"name\":\"event_data.WakeTimerOwnerLength\",\"type\":\"string\",\"count\":0,\"scripted\":false,\"searchable\":true,\"aggregatable\":true,\"readFromDocValues\":true},{\"name\":\"event_data.Workstation\",\"type\":\"string\",\"count\":0,\"scripted\":false,\"searchable\":true,\"aggregatable\":true,\"readFromDocValues\":true},{\"name\":\"event_data.WorkstationName\",\"type\":\"string\",\"count\":0,\"scripted\":false,\"searchable\":true,\"aggregatable\":true,\"readFromDocValues\":true},{\"name\":\"event_data.errorCode\",\"type\":\"string\",\"count\":0,\"scripted\":false,\"searchable\":true,\"aggregatable\":true,\"readFromDocValues\":true},{\"name\":\"event_data.param1\",\"type\":\"string\",\"count\":0,\"scripted\":false,\"searchable\":true,\"aggregatable\":true,\"readFromDocValues\":true},{\"name\":\"event_data.param10\",\"type\":\"string\",\"count\":0,\"scripted\":false,\"searchable\":true,\"aggregatable\":true,\"readFromDocValues\":true},{\"name\":\"event_data.param11\",\"type\":\"string\",\"count\":0,\"scripted\":false,\"searchable\":true,\"aggregatable\":true,\"readFromDocValues\":true},{\"name\":\"event_data.param12\",\"type\":\"string\",\"count\":0,\"scripted\":false,\"searchable\":true,\"aggregatable\":true,\"readFromDocValues\":true},{\"name\":\"event_data.param13\",\"type\":\"string\",\"count\":0,\"scripted\":false,\"searchable\":true,\"aggregatable\":true,\"readFromDocValues\":true},{\"name\":\"event_data.param14\",\"type\":\"string\",\"count\":0,\"scripted\":false,\"searchable\":true,\"aggregatable\":true,\"readFromDocValues\":true},{\"name\":\"event_data.param15\",\"type\":\"string\",\"count\":0,\"scripted\":false,\"searchable\":true,\"aggregatable\":true,\"readFromDocValues\":true},{\"name\":\"event_data.param16\",\"type\":\"string\",\"count\":0,\"scripted\":false,\"searchable\":true,\"aggregatable\":true,\"readFromDocValues\":true},{\"name\":\"event_data.param17\",\"type\":\"string\",\"count\":0,\"scripted\":false,\"searchable\":true,\"aggregatable\":true,\"readFromDocValues\":true},{\"name\":\"event_data.param19\",\"type\":\"string\",\"count\":0,\"scripted\":false,\"searchable\":true,\"aggregatable\":true,\"readFromDocValues\":true},{\"name\":\"event_data.param2\",\"type\":\"string\",\"count\":0,\"scripted\":false,\"searchable\":true,\"aggregatable\":true,\"readFromDocValues\":true},{\"name\":\"event_data.param20\",\"type\":\"string\",\"count\":0,\"scripted\":false,\"searchable\":true,\"aggregatable\":true,\"readFromDocValues\":true},{\"name\":\"event_data.param21\",\"type\":\"string\",\"count\":0,\"scripted\":false,\"searchable\":true,\"aggregatable\":true,\"readFromDocValues\":true},{\"name\":\"event_data.param22\",\"type\":\"string\",\"count\":0,\"scripted\":false,\"searchable\":true,\"aggregatable\":true,\"readFromDocValues\":true},{\"name\":\"event_data.param3\",\"type\":\"string\",\"count\":0,\"scripted\":false,\"searchable\":true,\"aggregatable\":true,\"readFromDocValues\":true},{\"name\":\"event_data.param4\",\"type\":\"string\",\"count\":0,\"scripted\":false,\"searchable\":true,\"aggregatable\":true,\"readFromDocValues\":true},{\"name\":\"event_data.param5\",\"type\":\"string\",\"count\":0,\"scripted\":false,\"searchable\":true,\"aggregatable\":true,\"readFromDocValues\":true},{\"name\":\"event_data.param6\",\"type\":\"string\",\"count\":0,\"scripted\":false,\"searchable\":true,\"aggregatable\":true,\"readFromDocValues\":true},{\"name\":\"event_data.param7\",\"type\":\"string\",\"count\":0,\"scripted\":false,\"searchable\":true,\"aggregatable\":true,\"readFromDocValues\":true},{\"name\":\"event_data.param8\",\"type\":\"string\",\"count\":0,\"scripted\":false,\"searchable\":true,\"aggregatable\":true,\"readFromDocValues\":true},{\"name\":\"event_data.param9\",\"type\":\"string\",\"count\":0,\"scripted\":false,\"searchable\":true,\"aggregatable\":true,\"readFromDocValues\":true},{\"name\":\"event_data.serviceGuid\",\"type\":\"string\",\"count\":0,\"scripted\":false,\"searchable\":true,\"aggregatable\":true,\"readFromDocValues\":true},{\"name\":\"event_data.updateGuid\",\"type\":\"string\",\"count\":0,\"scripted\":false,\"searchable\":true,\"aggregatable\":true,\"readFromDocValues\":true},{\"name\":\"event_data.updateRevisionNumber\",\"type\":\"string\",\"count\":0,\"scripted\":false,\"searchable\":true,\"aggregatable\":true,\"readFromDocValues\":true},{\"name\":\"event_data.updateTitle\",\"type\":\"string\",\"count\":0,\"scripted\":false,\"searchable\":true,\"aggregatable\":true,\"readFromDocValues\":true},{\"name\":\"event_id\",\"type\":\"number\",\"count\":2,\"scripted\":false,\"searchable\":true,\"aggregatable\":true,\"readFromDocValues\":true},{\"name\":\"host\",\"type\":\"string\",\"count\":0,\"scripted\":false,\"searchable\":true,\"aggregatable\":true,\"readFromDocValues\":true},{\"name\":\"keywords\",\"type\":\"string\",\"count\":0,\"scripted\":false,\"searchable\":true,\"aggregatable\":true,\"readFromDocValues\":true},{\"name\":\"kubernetes.container.image\",\"type\":\"string\",\"count\":0,\"scripted\":false,\"searchable\":true,\"aggregatable\":true,\"readFromDocValues\":true},{\"name\":\"kubernetes.container.name\",\"type\":\"string\",\"count\":0,\"scripted\":false,\"searchable\":true,\"aggregatable\":true,\"readFromDocValues\":true},{\"name\":\"kubernetes.namespace\",\"type\":\"string\",\"count\":0,\"scripted\":false,\"searchable\":true,\"aggregatable\":true,\"readFromDocValues\":true},{\"name\":\"kubernetes.pod.name\",\"type\":\"string\",\"count\":0,\"scripted\":false,\"searchable\":true,\"aggregatable\":true,\"readFromDocValues\":true},{\"name\":\"level\",\"type\":\"string\",\"count\":0,\"scripted\":false,\"searchable\":true,\"aggregatable\":true,\"readFromDocValues\":true},{\"name\":\"log_name\",\"type\":\"string\",\"count\":0,\"scripted\":false,\"searchable\":true,\"aggregatable\":true,\"readFromDocValues\":true},{\"name\":\"message\",\"type\":\"string\",\"count\":1,\"scripted\":false,\"searchable\":true,\"aggregatable\":false,\"readFromDocValues\":false},{\"name\":\"message_error\",\"type\":\"string\",\"count\":0,\"scripted\":false,\"searchable\":true,\"aggregatable\":true,\"readFromDocValues\":true},{\"name\":\"meta.cloud.availability_zone\",\"type\":\"string\",\"count\":0,\"scripted\":false,\"searchable\":true,\"aggregatable\":true,\"readFromDocValues\":true},{\"name\":\"meta.cloud.instance_id\",\"type\":\"string\",\"count\":0,\"scripted\":false,\"searchable\":true,\"aggregatable\":true,\"readFromDocValues\":true},{\"name\":\"meta.cloud.instance_name\",\"type\":\"string\",\"count\":0,\"scripted\":false,\"searchable\":true,\"aggregatable\":true,\"readFromDocValues\":true},{\"name\":\"meta.cloud.machine_type\",\"type\":\"string\",\"count\":0,\"scripted\":false,\"searchable\":true,\"aggregatable\":true,\"readFromDocValues\":true},{\"name\":\"meta.cloud.project_id\",\"type\":\"string\",\"count\":0,\"scripted\":false,\"searchable\":true,\"aggregatable\":true,\"readFromDocValues\":true},{\"name\":\"meta.cloud.provider\",\"type\":\"string\",\"count\":0,\"scripted\":false,\"searchable\":true,\"aggregatable\":true,\"readFromDocValues\":true},{\"name\":\"meta.cloud.region\",\"type\":\"string\",\"count\":0,\"scripted\":false,\"searchable\":true,\"aggregatable\":true,\"readFromDocValues\":true},{\"name\":\"opcode\",\"type\":\"string\",\"count\":0,\"scripted\":false,\"searchable\":true,\"aggregatable\":true,\"readFromDocValues\":true},{\"name\":\"process_id\",\"type\":\"number\",\"count\":0,\"scripted\":false,\"searchable\":true,\"aggregatable\":true,\"readFromDocValues\":true},{\"name\":\"provider_guid\",\"type\":\"string\",\"count\":0,\"scripted\":false,\"searchable\":true,\"aggregatable\":true,\"readFromDocValues\":true},{\"name\":\"record_number\",\"type\":\"string\",\"count\":0,\"scripted\":false,\"searchable\":true,\"aggregatable\":true,\"readFromDocValues\":true},{\"name\":\"related_activity_id\",\"type\":\"string\",\"count\":0,\"scripted\":false,\"searchable\":true,\"aggregatable\":true,\"readFromDocValues\":true},{\"name\":\"source_name\",\"type\":\"string\",\"count\":0,\"scripted\":false,\"searchable\":true,\"aggregatable\":true,\"readFromDocValues\":true},{\"name\":\"tags\",\"type\":\"string\",\"count\":0,\"scripted\":false,\"searchable\":true,\"aggregatable\":true,\"readFromDocValues\":true},{\"name\":\"task\",\"type\":\"string\",\"count\":0,\"scripted\":false,\"searchable\":true,\"aggregatable\":true,\"readFromDocValues\":true},{\"name\":\"thread_id\",\"type\":\"number\",\"count\":0,\"scripted\":false,\"searchable\":true,\"aggregatable\":true,\"readFromDocValues\":true},{\"name\":\"type\",\"type\":\"string\",\"count\":0,\"scripted\":false,\"searchable\":true,\"aggregatable\":true,\"readFromDocValues\":true},{\"name\":\"user.domain\",\"type\":\"string\",\"count\":0,\"scripted\":false,\"searchable\":true,\"aggregatable\":true,\"readFromDocValues\":true},{\"name\":\"user.identifier\",\"type\":\"string\",\"count\":0,\"scripted\":false,\"searchable\":true,\"aggregatable\":true,\"readFromDocValues\":true},{\"name\":\"user.name\",\"type\":\"string\",\"count\":0,\"scripted\":false,\"searchable\":true,\"aggregatable\":true,\"readFromDocValues\":true},{\"name\":\"user.type\",\"type\":\"string\",\"count\":0,\"scripted\":false,\"searchable\":true,\"aggregatable\":true,\"readFromDocValues\":true},{\"name\":\"user_data.AddServiceStatus\",\"type\":\"string\",\"count\":0,\"scripted\":false,\"searchable\":true,\"aggregatable\":true,\"readFromDocValues\":true},{\"name\":\"user_data.Dependency\",\"type\":\"string\",\"count\":0,\"scripted\":false,\"searchable\":true,\"aggregatable\":true,\"readFromDocValues\":true},{\"name\":\"user_data.DeviceId\",\"type\":\"string\",\"count\":0,\"scripted\":false,\"searchable\":true,\"aggregatable\":true,\"readFromDocValues\":true},{\"name\":\"user_data.DeviceInstanceID\",\"type\":\"string\",\"count\":0,\"scripted\":false,\"searchable\":true,\"aggregatable\":true,\"readFromDocValues\":true},{\"name\":\"user_data.DriverDescription\",\"type\":\"string\",\"count\":0,\"scripted\":false,\"searchable\":true,\"aggregatable\":true,\"readFromDocValues\":true},{\"name\":\"user_data.DriverFileName\",\"type\":\"string\",\"count\":0,\"scripted\":false,\"searchable\":true,\"aggregatable\":true,\"readFromDocValues\":true},{\"name\":\"user_data.DriverName\",\"type\":\"string\",\"count\":0,\"scripted\":false,\"searchable\":true,\"aggregatable\":true,\"readFromDocValues\":true},{\"name\":\"user_data.DriverProvider\",\"type\":\"string\",\"count\":0,\"scripted\":false,\"searchable\":true,\"aggregatable\":true,\"readFromDocValues\":true},{\"name\":\"user_data.DriverVersion\",\"type\":\"string\",\"count\":0,\"scripted\":false,\"searchable\":true,\"aggregatable\":true,\"readFromDocValues\":true},{\"name\":\"user_data.FinalStatus\",\"type\":\"string\",\"count\":0,\"scripted\":false,\"searchable\":true,\"aggregatable\":true,\"readFromDocValues\":true},{\"name\":\"user_data.InstallStatus\",\"type\":\"string\",\"count\":0,\"scripted\":false,\"searchable\":true,\"aggregatable\":true,\"readFromDocValues\":true},{\"name\":\"user_data.IsDriverOEM\",\"type\":\"string\",\"count\":0,\"scripted\":false,\"searchable\":true,\"aggregatable\":true,\"readFromDocValues\":true},{\"name\":\"user_data.MinimumFxVersion\",\"type\":\"string\",\"count\":0,\"scripted\":false,\"searchable\":true,\"aggregatable\":true,\"readFromDocValues\":true},{\"name\":\"user_data.PrimaryService\",\"type\":\"string\",\"count\":0,\"scripted\":false,\"searchable\":true,\"aggregatable\":true,\"readFromDocValues\":true},{\"name\":\"user_data.RebootOption\",\"type\":\"string\",\"count\":0,\"scripted\":false,\"searchable\":true,\"aggregatable\":true,\"readFromDocValues\":true},{\"name\":\"user_data.RmSessionId\",\"type\":\"string\",\"count\":0,\"scripted\":false,\"searchable\":true,\"aggregatable\":true,\"readFromDocValues\":true},{\"name\":\"user_data.ServiceName\",\"type\":\"string\",\"count\":0,\"scripted\":false,\"searchable\":true,\"aggregatable\":true,\"readFromDocValues\":true},{\"name\":\"user_data.SetupClass\",\"type\":\"string\",\"count\":0,\"scripted\":false,\"searchable\":true,\"aggregatable\":true,\"readFromDocValues\":true},{\"name\":\"user_data.UTCStartTime\",\"type\":\"string\",\"count\":0,\"scripted\":false,\"searchable\":true,\"aggregatable\":true,\"readFromDocValues\":true},{\"name\":\"user_data.UpdateService\",\"type\":\"string\",\"count\":0,\"scripted\":false,\"searchable\":true,\"aggregatable\":true,\"readFromDocValues\":true},{\"name\":\"user_data.UpgradeDevice\",\"type\":\"string\",\"count\":0,\"scripted\":false,\"searchable\":true,\"aggregatable\":true,\"readFromDocValues\":true},{\"name\":\"user_data.xml_name\",\"type\":\"string\",\"count\":0,\"scripted\":false,\"searchable\":true,\"aggregatable\":true,\"readFromDocValues\":true},{\"name\":\"version\",\"type\":\"number\",\"count\":0,\"scripted\":false,\"searchable\":true,\"aggregatable\":true,\"readFromDocValues\":true},{\"name\":\"xml\",\"type\":\"string\",\"count\":0,\"scripted\":false,\"searchable\":true,\"aggregatable\":false,\"readFromDocValues\":false}]",
        "timeFieldName": "@timestamp",
        "title": "winlogbeat-*"
      }
    },
    {
      "id": "NMAP-common-search",
      "type": "search",
      "updated_at": "2018-02-05T11:46:27.910Z",
      "version": 2,
      "attributes": {
        "title": "NMAP-common-search",
        "description": "",
        "hits": 0,
        "columns": [
          "ipv4",
          "port.number",
          "hostname.name",
          "port.service.name",
          "port.state"
        ],
        "sort": [
          "@timestamp",
          "desc"
        ],
        "version": 1,
        "kibanaSavedObjectMeta": {
          "searchSourceJSON": "{\"index\":\"nmap-*\",\"query\":{\"query\":{\"query_string\":{\"analyze_wildcard\":true,\"query\":\"*\",\"default_field\":\"*\"}},\"language\":\"lucene\"},\"filter\":[],\"highlight\":{\"pre_tags\":[\"@kibana-highlighted-field@\"],\"post_tags\":[\"@/kibana-highlighted-field@\"],\"fields\":{\"*\":{}},\"require_field_match\":false,\"fragment_size\":2147483647},\"highlightAll\":true,\"version\":true}"
        }
      }
    },
    {
      "id": "nmap-*",
      "type": "index-pattern",
      "updated_at": "2018-02-05T11:45:45.369Z",
      "version": 3,
      "attributes": {
        "title": "nmap-*",
        "timeFieldName": "@timestamp",
        "fields": "[{\"name\":\"@timestamp\",\"type\":\"date\",\"count\":0,\"scripted\":false,\"searchable\":true,\"aggregatable\":true,\"readFromDocValues\":true},{\"name\":\"@version\",\"type\":\"string\",\"count\":0,\"scripted\":false,\"searchable\":true,\"aggregatable\":true,\"readFromDocValues\":true},{\"name\":\"_id\",\"type\":\"string\",\"count\":0,\"scripted\":false,\"searchable\":true,\"aggregatable\":true,\"readFromDocValues\":false},{\"name\":\"_index\",\"type\":\"string\",\"count\":0,\"scripted\":false,\"searchable\":true,\"aggregatable\":true,\"readFromDocValues\":false},{\"name\":\"_score\",\"type\":\"number\",\"count\":0,\"scripted\":false,\"searchable\":false,\"aggregatable\":false,\"readFromDocValues\":false},{\"name\":\"_source\",\"type\":\"_source\",\"count\":0,\"scripted\":false,\"searchable\":false,\"aggregatable\":false,\"readFromDocValues\":false},{\"name\":\"_type\",\"type\":\"string\",\"count\":0,\"scripted\":false,\"searchable\":true,\"aggregatable\":true,\"readFromDocValues\":false},{\"name\":\"address\",\"type\":\"string\",\"count\":0,\"scripted\":false,\"searchable\":true,\"aggregatable\":true,\"readFromDocValues\":true},{\"name\":\"addresses.addr\",\"type\":\"string\",\"count\":0,\"scripted\":false,\"searchable\":true,\"aggregatable\":true,\"readFromDocValues\":true},{\"name\":\"addresses.type\",\"type\":\"string\",\"count\":0,\"scripted\":false,\"searchable\":true,\"aggregatable\":true,\"readFromDocValues\":true},{\"name\":\"arguments\",\"type\":\"string\",\"count\":0,\"scripted\":false,\"searchable\":true,\"aggregatable\":true,\"readFromDocValues\":true},{\"name\":\"end_time\",\"type\":\"date\",\"count\":0,\"scripted\":false,\"searchable\":true,\"aggregatable\":true,\"readFromDocValues\":true},{\"name\":\"headers.http_x_nmap_target\",\"type\":\"string\",\"count\":0,\"scripted\":false,\"searchable\":true,\"aggregatable\":true,\"readFromDocValues\":true},{\"name\":\"host_stats.down\",\"type\":\"number\",\"count\":0,\"scripted\":false,\"searchable\":true,\"aggregatable\":true,\"readFromDocValues\":true},{\"name\":\"host_stats.total\",\"type\":\"number\",\"count\":0,\"scripted\":false,\"searchable\":true,\"aggregatable\":true,\"readFromDocValues\":true},{\"name\":\"host_stats.up\",\"type\":\"number\",\"count\":0,\"scripted\":false,\"searchable\":true,\"aggregatable\":true,\"readFromDocValues\":true},{\"name\":\"hostname.name\",\"type\":\"string\",\"count\":0,\"scripted\":false,\"searchable\":true,\"aggregatable\":true,\"readFromDocValues\":true},{\"name\":\"hostname.type\",\"type\":\"string\",\"count\":0,\"scripted\":false,\"searchable\":true,\"aggregatable\":true,\"readFromDocValues\":true},{\"name\":\"id\",\"type\":\"string\",\"count\":0,\"scripted\":false,\"searchable\":true,\"aggregatable\":true,\"readFromDocValues\":true},{\"name\":\"ip\",\"type\":\"string\",\"count\":0,\"scripted\":false,\"searchable\":true,\"aggregatable\":true,\"readFromDocValues\":true},{\"name\":\"ipv4\",\"type\":\"ip\",\"count\":0,\"scripted\":false,\"searchable\":true,\"aggregatable\":true,\"readFromDocValues\":true},{\"name\":\"ipv6\",\"type\":\"ip\",\"count\":0,\"scripted\":false,\"searchable\":true,\"aggregatable\":true,\"readFromDocValues\":true},{\"name\":\"mac\",\"type\":\"string\",\"count\":0,\"scripted\":false,\"searchable\":true,\"aggregatable\":true,\"readFromDocValues\":true},{\"name\":\"port.number\",\"type\":\"number\",\"count\":0,\"scripted\":false,\"searchable\":true,\"aggregatable\":true,\"readFromDocValues\":true},{\"name\":\"port.protocol\",\"type\":\"string\",\"count\":0,\"scripted\":false,\"searchable\":true,\"aggregatable\":true,\"readFromDocValues\":true},{\"name\":\"port.reason\",\"type\":\"string\",\"count\":0,\"scripted\":false,\"searchable\":true,\"aggregatable\":true,\"readFromDocValues\":true},{\"name\":\"port.service.confidence\",\"type\":\"number\",\"count\":0,\"scripted\":false,\"searchable\":true,\"aggregatable\":true,\"readFromDocValues\":true},{\"name\":\"port.service.fingerprint_method\",\"type\":\"string\",\"count\":0,\"scripted\":false,\"searchable\":true,\"aggregatable\":true,\"readFromDocValues\":true},{\"name\":\"port.service.name\",\"type\":\"string\",\"count\":0,\"scripted\":false,\"searchable\":true,\"aggregatable\":true,\"readFromDocValues\":true},{\"name\":\"port.service.ssl\",\"type\":\"boolean\",\"count\":0,\"scripted\":false,\"searchable\":true,\"aggregatable\":true,\"readFromDocValues\":true},{\"name\":\"port.state\",\"type\":\"string\",\"count\":0,\"scripted\":false,\"searchable\":true,\"aggregatable\":true,\"readFromDocValues\":true},{\"name\":\"ports.number\",\"type\":\"number\",\"count\":0,\"scripted\":false,\"searchable\":true,\"aggregatable\":true,\"readFromDocValues\":true},{\"name\":\"ports.protocol\",\"type\":\"string\",\"count\":0,\"scripted\":false,\"searchable\":true,\"aggregatable\":true,\"readFromDocValues\":true},{\"name\":\"ports.reason\",\"type\":\"string\",\"count\":0,\"scripted\":false,\"searchable\":true,\"aggregatable\":true,\"readFromDocValues\":true},{\"name\":\"ports.service.confidence\",\"type\":\"number\",\"count\":0,\"scripted\":false,\"searchable\":true,\"aggregatable\":true,\"readFromDocValues\":true},{\"name\":\"ports.service.fingerprint_method\",\"type\":\"string\",\"count\":0,\"scripted\":false,\"searchable\":true,\"aggregatable\":true,\"readFromDocValues\":true},{\"name\":\"ports.service.name\",\"type\":\"string\",\"count\":0,\"scripted\":false,\"searchable\":true,\"aggregatable\":true,\"readFromDocValues\":true},{\"name\":\"ports.service.ssl\",\"type\":\"boolean\",\"count\":0,\"scripted\":false,\"searchable\":true,\"aggregatable\":true,\"readFromDocValues\":true},{\"name\":\"ports.state\",\"type\":\"string\",\"count\":0,\"scripted\":false,\"searchable\":true,\"aggregatable\":true,\"readFromDocValues\":true},{\"name\":\"scan_host_id\",\"type\":\"string\",\"count\":0,\"scripted\":false,\"searchable\":true,\"aggregatable\":true,\"readFromDocValues\":true},{\"name\":\"scan_id\",\"type\":\"string\",\"count\":0,\"scripted\":false,\"searchable\":true,\"aggregatable\":true,\"readFromDocValues\":true},{\"name\":\"start_time\",\"type\":\"date\",\"count\":0,\"scripted\":false,\"searchable\":true,\"aggregatable\":true,\"readFromDocValues\":true},{\"name\":\"status.reason\",\"type\":\"string\",\"count\":0,\"scripted\":false,\"searchable\":true,\"aggregatable\":true,\"readFromDocValues\":true},{\"name\":\"status.state\",\"type\":\"string\",\"count\":0,\"scripted\":false,\"searchable\":true,\"aggregatable\":true,\"readFromDocValues\":true},{\"name\":\"tags\",\"type\":\"string\",\"count\":0,\"scripted\":false,\"searchable\":true,\"aggregatable\":false,\"readFromDocValues\":false},{\"name\":\"type\",\"type\":\"string\",\"count\":0,\"scripted\":false,\"searchable\":true,\"aggregatable\":true,\"readFromDocValues\":true},{\"name\":\"version\",\"type\":\"string\",\"count\":0,\"scripted\":false,\"searchable\":true,\"aggregatable\":true,\"readFromDocValues\":true},{\"name\":\"winlog_url\",\"type\":\"string\",\"count\":1,\"scripted\":false,\"searchable\":true,\"aggregatable\":true,\"readFromDocValues\":true}]"
      }
    },
    {
      "id": "0064c570-0a6c-11e8-a2ce-b9829bf5932d",
      "type": "dashboard",
      "updated_at": "2018-02-05T13:58:36.173Z",
      "version": 2,
      "attributes": {
        "title": "Main Dashboard",
        "hits": 0,
        "description": "",
        "panelsJSON": "[{\"panelIndex\":\"1\",\"gridData\":{\"x\":0,\"y\":0,\"w\":3,\"h\":2,\"i\":\"1\"},\"id\":\"Number-of-Events\",\"title\":\"Windows к-во событий\",\"type\":\"visualization\",\"version\":\"6.1.3\"},{\"panelIndex\":\"2\",\"gridData\":{\"x\":0,\"y\":2,\"w\":3,\"h\":3,\"i\":\"2\"},\"id\":\"Number-of-Events-Over-Time-By-Event-Log\",\"title\":\"Windows Timeline\",\"type\":\"visualization\",\"version\":\"6.1.3\"},{\"panelIndex\":\"3\",\"gridData\":{\"x\":0,\"y\":5,\"w\":3,\"h\":3,\"i\":\"3\"},\"id\":\"NMAP-hosts-by-subnet-table\",\"title\":\"Хостов в сети\",\"type\":\"visualization\",\"version\":\"6.1.3\"},{\"title\":\"Ссылки и Справка\",\"panelIndex\":\"4\",\"gridData\":{\"x\":3,\"y\":0,\"w\":9,\"h\":8,\"i\":\"4\"},\"version\":\"6.1.3\",\"type\":\"visualization\",\"id\":\"f24a7060-0a7b-11e8-a2ce-b9829bf5932d\"}]",
        "optionsJSON": "{\"darkTheme\":false,\"hidePanelTitles\":false,\"useMargins\":true}",
        "uiStateJSON": "{\"P-2\":{\"vis\":{\"legendOpen\":false}},\"P-3\":{\"vis\":{\"params\":{\"sort\":{\"columnIndex\":null,\"direction\":null}}}}}",
        "version": 1,
        "timeRestore": true,
        "timeTo": "now",
        "timeFrom": "now-24h",
        "refreshInterval": {
          "display": "Off",
          "pause": false,
          "value": 0
        },
        "kibanaSavedObjectMeta": {
          "searchSourceJSON": "{\"query\":{\"language\":\"lucene\",\"query\":\"\"},\"filter\":[],\"highlightAll\":true,\"version\":true}"
        }
      }
    }
  ]
}