[
  {
    "_id": "179261d0-6d50-11e7-a3f5-eddd792e62e4",
    "_type": "visualization",
    "_source": {
      "title": "Wazh Всего событий",
      "visState": "{\"title\":\"Wazh Всего событий\",\"type\":\"metric\",\"params\":{\"addTooltip\":true,\"addLegend\":false,\"type\":\"gauge\",\"gauge\":{\"verticalSplit\":false,\"autoExtend\":false,\"percentageMode\":false,\"gaugeType\":\"Metric\",\"gaugeStyle\":\"Full\",\"backStyle\":\"Full\",\"orientation\":\"vertical\",\"colorSchema\":\"Green to Red\",\"gaugeColorMode\":\"None\",\"useRange\":false,\"colorsRange\":[{\"from\":0,\"to\":100}],\"invertColors\":false,\"labels\":{\"show\":true,\"color\":\"black\"},\"scale\":{\"show\":false,\"labels\":false,\"color\":\"#333\",\"width\":2},\"type\":\"simple\",\"style\":{\"fontSize\":\"48\",\"bgFill\":\"#000\",\"bgColor\":false,\"labelColor\":false,\"subText\":\"\"}}},\"aggs\":[{\"id\":\"1\",\"enabled\":true,\"type\":\"count\",\"schema\":\"metric\",\"params\":{\"customLabel\":\"кол-во\"}}],\"listeners\":{}}",
      "uiStateJSON": "{\"vis\":{\"defaultColors\":{\"0 - 100\":\"rgb(0,104,55)\"}}}",
      "description": "",
      "savedSearchId": "6ee6e880-6d4f-11e7-a3f5-eddd792e62e4",
      "version": 1,
      "kibanaSavedObjectMeta": {
        "searchSourceJSON": "{\"filter\":[]}"
      }
    }
  },
  {
    "_id": "ae1c7a90-6d51-11e7-a3f5-eddd792e62e4",
    "_type": "visualization",
    "_source": {
      "title": "Wazh Уровень событий",
      "visState": "{\"title\":\"Wazh Уровень событий\",\"type\":\"table\",\"params\":{\"perPage\":10,\"showPartialRows\":false,\"showMeticsAtAllLevels\":false,\"sort\":{\"columnIndex\":null,\"direction\":null},\"showTotal\":false,\"totalFunc\":\"sum\"},\"aggs\":[{\"id\":\"1\",\"enabled\":true,\"type\":\"count\",\"schema\":\"metric\",\"params\":{\"customLabel\":\"кол-во\"}},{\"id\":\"2\",\"enabled\":true,\"type\":\"terms\",\"schema\":\"bucket\",\"params\":{\"field\":\"rule.level\",\"size\":20,\"order\":\"desc\",\"orderBy\":\"_term\",\"customLabel\":\"Уровень\"}},{\"id\":\"4\",\"enabled\":true,\"type\":\"terms\",\"schema\":\"bucket\",\"params\":{\"field\":\"rule.description\",\"size\":300,\"order\":\"desc\",\"orderBy\":\"1\",\"customLabel\":\"Описание\"}}],\"listeners\":{}}",
      "uiStateJSON": "{\"vis\":{\"params\":{\"sort\":{\"columnIndex\":null,\"direction\":null}}}}",
      "description": "",
      "savedSearchId": "6ee6e880-6d4f-11e7-a3f5-eddd792e62e4",
      "version": 1,
      "kibanaSavedObjectMeta": {
        "searchSourceJSON": "{\"filter\":[]}"
      }
    }
  },
  {
    "_id": "4f8a77b0-6d52-11e7-a3f5-eddd792e62e4",
    "_type": "visualization",
    "_source": {
      "title": "Wazuh CIS",
      "visState": "{\"title\":\"Wazuh CIS\",\"type\":\"table\",\"params\":{\"perPage\":10,\"showPartialRows\":false,\"showMeticsAtAllLevels\":false,\"sort\":{\"columnIndex\":null,\"direction\":null},\"showTotal\":false,\"totalFunc\":\"sum\"},\"aggs\":[{\"id\":\"1\",\"enabled\":true,\"type\":\"count\",\"schema\":\"metric\",\"params\":{\"customLabel\":\"кол-во\"}},{\"id\":\"2\",\"enabled\":true,\"type\":\"terms\",\"schema\":\"bucket\",\"params\":{\"field\":\"rule.cis\",\"size\":300,\"order\":\"desc\",\"orderBy\":\"1\",\"customLabel\":\"CIS\"}},{\"id\":\"3\",\"enabled\":true,\"type\":\"terms\",\"schema\":\"bucket\",\"params\":{\"field\":\"title\",\"size\":300,\"order\":\"desc\",\"orderBy\":\"1\",\"customLabel\":\"Правило\"}}],\"listeners\":{}}",
      "uiStateJSON": "{\"vis\":{\"params\":{\"sort\":{\"columnIndex\":null,\"direction\":null}}}}",
      "description": "",
      "savedSearchId": "6ee6e880-6d4f-11e7-a3f5-eddd792e62e4",
      "version": 1,
      "kibanaSavedObjectMeta": {
        "searchSourceJSON": "{\"filter\":[]}"
      }
    }
  },
  {
    "_id": "d40f11c0-6d53-11e7-a3f5-eddd792e62e4",
    "_type": "visualization",
    "_source": {
      "title": "Wazuh CVE",
      "visState": "{\"title\":\"Wazuh CVE\",\"type\":\"table\",\"params\":{\"perPage\":10,\"showPartialRows\":false,\"showMeticsAtAllLevels\":false,\"sort\":{\"columnIndex\":null,\"direction\":null},\"showTotal\":false,\"totalFunc\":\"sum\"},\"aggs\":[{\"id\":\"1\",\"enabled\":true,\"type\":\"count\",\"schema\":\"metric\",\"params\":{\"customLabel\":\"кол-во\"}},{\"id\":\"2\",\"enabled\":true,\"type\":\"terms\",\"schema\":\"bucket\",\"params\":{\"field\":\"rule.cve\",\"size\":300,\"order\":\"desc\",\"orderBy\":\"1\",\"customLabel\":\"CVE\"}},{\"id\":\"3\",\"enabled\":true,\"type\":\"terms\",\"schema\":\"bucket\",\"params\":{\"field\":\"title\",\"size\":300,\"order\":\"desc\",\"orderBy\":\"1\",\"customLabel\":\"Название\"}}],\"listeners\":{}}",
      "uiStateJSON": "{\"vis\":{\"params\":{\"sort\":{\"columnIndex\":null,\"direction\":null}}}}",
      "description": "",
      "savedSearchId": "6ee6e880-6d4f-11e7-a3f5-eddd792e62e4",
      "version": 1,
      "kibanaSavedObjectMeta": {
        "searchSourceJSON": "{\"filter\":[]}"
      }
    }
  },
  {
    "_id": "3d199790-6d53-11e7-a3f5-eddd792e62e4",
    "_type": "visualization",
    "_source": {
      "title": "Wazuh PCI DSS",
      "visState": "{\"title\":\"Wazuh PCI DSS\",\"type\":\"table\",\"params\":{\"perPage\":10,\"showPartialRows\":false,\"showMeticsAtAllLevels\":false,\"sort\":{\"columnIndex\":null,\"direction\":null},\"showTotal\":false,\"totalFunc\":\"sum\"},\"aggs\":[{\"id\":\"1\",\"enabled\":true,\"type\":\"count\",\"schema\":\"metric\",\"params\":{\"customLabel\":\"кол-во\"}},{\"id\":\"2\",\"enabled\":true,\"type\":\"terms\",\"schema\":\"bucket\",\"params\":{\"field\":\"rule.pci_dss\",\"size\":200,\"order\":\"desc\",\"orderBy\":\"1\",\"customLabel\":\"PCI DSS\"}},{\"id\":\"3\",\"enabled\":true,\"type\":\"terms\",\"schema\":\"bucket\",\"params\":{\"field\":\"title\",\"size\":300,\"order\":\"desc\",\"orderBy\":\"1\",\"customLabel\":\"Правило\"}}],\"listeners\":{}}",
      "uiStateJSON": "{\"vis\":{\"params\":{\"sort\":{\"columnIndex\":null,\"direction\":null}}}}",
      "description": "",
      "savedSearchId": "6ee6e880-6d4f-11e7-a3f5-eddd792e62e4",
      "version": 1,
      "kibanaSavedObjectMeta": {
        "searchSourceJSON": "{\"filter\":[]}"
      }
    }
  },
  {
    "_id": "7515e8a0-6d54-11e7-a3f5-eddd792e62e4",
    "_type": "visualization",
    "_source": {
      "title": "Wazuh timeline",
      "visState": "{\"title\":\"Wazuh timeline\",\"type\":\"histogram\",\"params\":{\"grid\":{\"categoryLines\":false,\"style\":{\"color\":\"#eee\"}},\"categoryAxes\":[{\"id\":\"CategoryAxis-1\",\"type\":\"category\",\"position\":\"bottom\",\"show\":true,\"style\":{},\"scale\":{\"type\":\"linear\"},\"labels\":{\"show\":true,\"truncate\":100},\"title\":{\"text\":\"@timestamp per 30 minutes\"}}],\"valueAxes\":[{\"id\":\"ValueAxis-1\",\"name\":\"LeftAxis-1\",\"type\":\"value\",\"position\":\"left\",\"show\":true,\"style\":{},\"scale\":{\"type\":\"linear\",\"mode\":\"normal\"},\"labels\":{\"show\":true,\"rotate\":0,\"filter\":false,\"truncate\":100},\"title\":{\"text\":\"кол-во\"}}],\"seriesParams\":[{\"show\":\"true\",\"type\":\"histogram\",\"mode\":\"stacked\",\"data\":{\"label\":\"кол-во\",\"id\":\"1\"},\"valueAxis\":\"ValueAxis-1\",\"drawLinesBetweenPoints\":true,\"showCircles\":true}],\"addTooltip\":true,\"addLegend\":true,\"legendPosition\":\"right\",\"times\":[],\"addTimeMarker\":false},\"aggs\":[{\"id\":\"1\",\"enabled\":true,\"type\":\"count\",\"schema\":\"metric\",\"params\":{\"customLabel\":\"кол-во\"}},{\"id\":\"2\",\"enabled\":true,\"type\":\"date_histogram\",\"schema\":\"segment\",\"params\":{\"field\":\"@timestamp\",\"interval\":\"auto\",\"customInterval\":\"2h\",\"min_doc_count\":1,\"extended_bounds\":{}}}],\"listeners\":{}}",
      "uiStateJSON": "{\"vis\":{\"colors\":{\"кол-во\":\"#447EBC\"}}}",
      "description": "",
      "savedSearchId": "6ee6e880-6d4f-11e7-a3f5-eddd792e62e4",
      "version": 1,
      "kibanaSavedObjectMeta": {
        "searchSourceJSON": "{\"filter\":[]}"
      }
    }
  },
  {
    "_id": "36c5c2a0-6d54-11e7-a3f5-eddd792e62e4",
    "_type": "visualization",
    "_source": {
      "title": "Wazuh по хостам",
      "visState": "{\"title\":\"Wazuh по хостам\",\"type\":\"table\",\"params\":{\"perPage\":10,\"showPartialRows\":false,\"showMeticsAtAllLevels\":false,\"sort\":{\"columnIndex\":null,\"direction\":null},\"showTotal\":false,\"totalFunc\":\"sum\"},\"aggs\":[{\"id\":\"1\",\"enabled\":true,\"type\":\"count\",\"schema\":\"metric\",\"params\":{\"customLabel\":\"кол-во\"}},{\"id\":\"2\",\"enabled\":true,\"type\":\"terms\",\"schema\":\"bucket\",\"params\":{\"field\":\"host\",\"size\":1000,\"order\":\"desc\",\"orderBy\":\"1\",\"customLabel\":\"Хост\"}}],\"listeners\":{}}",
      "uiStateJSON": "{\"vis\":{\"params\":{\"sort\":{\"columnIndex\":null,\"direction\":null}}}}",
      "description": "",
      "savedSearchId": "6ee6e880-6d4f-11e7-a3f5-eddd792e62e4",
      "version": 1,
      "kibanaSavedObjectMeta": {
        "searchSourceJSON": "{\"filter\":[]}"
      }
    }
  }
]